[{"id":3794,"t":"וַיֹּ֤אמֶר","p":"ויאמר","c":12,"v":1},{"id":3795,"t":"יְהֹוָה֙","p":"יהוה","c":12,"v":1},{"id":3796,"t":"אֶל","p":"אל","c":12,"v":1},{"id":3797,"t":"אַבְרָ֔ם","p":"אברם","c":12,"v":1},{"id":3798,"t":"לֶךְ","p":"לך","c":12,"v":1},{"id":3799,"t":"לְךָ֛","p":"לך","c":12,"v":1},{"id":3800,"t":"מֵאַרְצְךָ֥","p":"מארצך","c":12,"v":1},{"id":3801,"t":"וּמִמּֽוֹלַדְתְּךָ֖","p":"וממולדתך","c":12,"v":1},{"id":3802,"t":"וּמִבֵּ֣ית","p":"ומבית","c":12,"v":1},{"id":3803,"t":"אָבִ֑יךָ","p":"אביך","c":12,"v":1},{"id":3804,"t":"אֶל","p":"אל","c":12,"v":1},{"id":3805,"t":"הָאָ֖רֶץ","p":"הארץ","c":12,"v":1},{"id":3806,"t":"אֲשֶׁ֥ר","p":"אשר","c":12,"v":1},{"id":3807,"t":"אַרְאֶֽךָּ","p":"אראך","c":12,"v":1},{"id":3808,"t":"וְאֶֽעֶשְׂךָ֙","p":"ואעשך","c":12,"v":2},{"id":3809,"t":"לְג֣וֹי","p":"לגוי","c":12,"v":2},{"id":3810,"t":"גָּד֔וֹל","p":"גדול","c":12,"v":2},{"id":3811,"t":"וַאֲבָ֣רֶכְךָ֔","p":"ואברכך","c":12,"v":2},{"id":3812,"t":"וַאֲגַדְּלָ֖ה","p":"ואגדלה","c":12,"v":2},{"id":3813,"t":"שְׁמֶ֑ךָ","p":"שמך","c":12,"v":2},{"id":3814,"t":"וֶהְיֵ֖ה","p":"והיה","c":12,"v":2},{"id":3815,"t":"בְּרָכָֽה","p":"ברכה","c":12,"v":2},{"id":3816,"t":"וַאֲבָֽרְכָה֙","p":"ואברכה","c":12,"v":3},{"id":3817,"t":"מְבָ֣רְכֶ֔יךָ","p":"מברכיך","c":12,"v":3},{"id":3818,"t":"וּמְקַלֶּלְךָ֖","p":"ומקללך","c":12,"v":3},{"id":3819,"t":"אָאֹ֑ר","p":"אאר","c":12,"v":3},{"id":3820,"t":"וְנִבְרְכ֣וּ","p":"ונברכו","c":12,"v":3},{"id":3821,"t":"בְךָ֔","p":"בך","c":12,"v":3},{"id":3822,"t":"כֹּ֖ל","p":"כל","c":12,"v":3},{"id":3823,"t":"מִשְׁפְּחֹ֥ת","p":"משפחת","c":12,"v":3},{"id":3824,"t":"הָאֲדָמָֽה","p":"האדמה","c":12,"v":3},{"id":3825,"t":"וַיֵּ֣לֶךְ","p":"וילך","c":12,"v":4},{"id":3826,"t":"אַבְרָ֗ם","p":"אברם","c":12,"v":4},{"id":3827,"t":"כַּאֲשֶׁ֨ר","p":"כאשר","c":12,"v":4},{"id":3828,"t":"דִּבֶּ֤ר","p":"דבר","c":12,"v":4},{"id":3829,"t":"אֵלָיו֙","p":"אליו","c":12,"v":4},{"id":3830,"t":"יְהֹוָ֔ה","p":"יהוה","c":12,"v":4},{"id":3831,"t":"וַיֵּ֥לֶךְ","p":"וילך","c":12,"v":4},{"id":3832,"t":"אִתּ֖וֹ","p":"אתו","c":12,"v":4},{"id":3833,"t":"ל֑וֹט","p":"לוט","c":12,"v":4},{"id":3834,"t":"וְאַבְרָ֗ם","p":"ואברם","c":12,"v":4},{"id":3835,"t":"בֶּן","p":"בן","c":12,"v":4},{"id":3836,"t":"חָמֵ֤שׁ","p":"חמש","c":12,"v":4},{"id":3837,"t":"שָׁנִים֙","p":"שנים","c":12,"v":4},{"id":3838,"t":"וְשִׁבְעִ֣ים","p":"ושבעים","c":12,"v":4},{"id":3839,"t":"שָׁנָ֔ה","p":"שנה","c":12,"v":4},{"id":3840,"t":"בְּצֵאת֖וֹ","p":"בצאתו","c":12,"v":4},{"id":3841,"t":"מֵחָרָֽן","p":"מחרן","c":12,"v":4},{"id":3842,"t":"וַיִּקַּ֣ח","p":"ויקח","c":12,"v":5},{"id":3843,"t":"אַבְרָם֩","p":"אברם","c":12,"v":5},{"id":3844,"t":"אֶת","p":"את","c":12,"v":5},{"id":3845,"t":"שָׂרַ֨י","p":"שרי","c":12,"v":5},{"id":3846,"t":"אִשְׁתּ֜וֹ","p":"אשתו","c":12,"v":5},{"id":3847,"t":"וְאֶת","p":"ואת","c":12,"v":5},{"id":3848,"t":"ל֣וֹט","p":"לוט","c":12,"v":5},{"id":3849,"t":"בֶּן","p":"בן","c":12,"v":5},{"id":3850,"t":"אָחִ֗יו","p":"אחיו","c":12,"v":5},{"id":3851,"t":"וְאֶת","p":"ואת","c":12,"v":5},{"id":3852,"t":"כׇּל","p":"כל","c":12,"v":5},{"id":3853,"t":"רְכוּשָׁם֙","p":"רכושם","c":12,"v":5},{"id":3854,"t":"אֲשֶׁ֣ר","p":"אשר","c":12,"v":5},{"id":3855,"t":"רָכָ֔שׁוּ","p":"רכשו","c":12,"v":5},{"id":3856,"t":"וְאֶת","p":"ואת","c":12,"v":5},{"id":3857,"t":"הַנֶּ֖פֶשׁ","p":"הנפש","c":12,"v":5},{"id":3858,"t":"אֲשֶׁר","p":"אשר","c":12,"v":5},{"id":3859,"t":"עָשׂ֣וּ","p":"עשו","c":12,"v":5},{"id":3860,"t":"בְחָרָ֑ן","p":"בחרן","c":12,"v":5},{"id":3861,"t":"וַיֵּצְא֗וּ","p":"ויצאו","c":12,"v":5},{"id":3862,"t":"לָלֶ֙כֶת֙","p":"ללכת","c":12,"v":5},{"id":3863,"t":"אַ֣רְצָה","p":"ארצה","c":12,"v":5},{"id":3864,"t":"כְּנַ֔עַן","p":"כנען","c":12,"v":5},{"id":3865,"t":"וַיָּבֹ֖אוּ","p":"ויבאו","c":12,"v":5},{"id":3866,"t":"אַ֥רְצָה","p":"ארצה","c":12,"v":5},{"id":3867,"t":"כְּנָֽעַן","p":"כנען","c":12,"v":5},{"id":3868,"t":"וַיַּעֲבֹ֤ר","p":"ויעבר","c":12,"v":6},{"id":3869,"t":"אַבְרָם֙","p":"אברם","c":12,"v":6},{"id":3870,"t":"בָּאָ֔רֶץ","p":"בארץ","c":12,"v":6},{"id":3871,"t":"עַ֚ד","p":"עד","c":12,"v":6},{"id":3872,"t":"מְק֣וֹם","p":"מקום","c":12,"v":6},{"id":3873,"t":"שְׁכֶ֔ם","p":"שכם","c":12,"v":6},{"id":3874,"t":"עַ֖ד","p":"עד","c":12,"v":6},{"id":3875,"t":"אֵל֣וֹן","p":"אלון","c":12,"v":6},{"id":3876,"t":"מוֹרֶ֑ה","p":"מורה","c":12,"v":6},{"id":3877,"t":"וְהַֽכְּנַעֲנִ֖י","p":"והכנעני","c":12,"v":6},{"id":3878,"t":"אָ֥ז","p":"אז","c":12,"v":6},{"id":3879,"t":"בָּאָֽרֶץ","p":"בארץ","c":12,"v":6},{"id":3880,"t":"וַיֵּרָ֤א","p":"וירא","c":12,"v":7},{"id":3881,"t":"יְהֹוָה֙","p":"יהוה","c":12,"v":7},{"id":3882,"t":"אֶל","p":"אל","c":12,"v":7},{"id":3883,"t":"אַבְרָ֔ם","p":"אברם","c":12,"v":7},{"id":3884,"t":"וַיֹּ֕אמֶר","p":"ויאמר","c":12,"v":7},{"id":3885,"t":"לְזַ֨רְעֲךָ֔","p":"לזרעך","c":12,"v":7},{"id":3886,"t":"אֶתֵּ֖ן","p":"אתן","c":12,"v":7},{"id":3887,"t":"אֶת","p":"את","c":12,"v":7},{"id":3888,"t":"הָאָ֣רֶץ","p":"הארץ","c":12,"v":7},{"id":3889,"t":"הַזֹּ֑את","p":"הזאת","c":12,"v":7},{"id":3890,"t":"וַיִּ֤בֶן","p":"ויבן","c":12,"v":7},{"id":3891,"t":"שָׁם֙","p":"שם","c":12,"v":7},{"id":3892,"t":"מִזְבֵּ֔חַ","p":"מזבח","c":12,"v":7},{"id":3893,"t":"לַיהֹוָ֖ה","p":"ליהוה","c":12,"v":7},{"id":3894,"t":"הַנִּרְאֶ֥ה","p":"הנראה","c":12,"v":7},{"id":3895,"t":"אֵלָֽיו","p":"אליו","c":12,"v":7},{"id":3896,"t":"וַיַּעְתֵּ֨ק","p":"ויעתק","c":12,"v":8},{"id":3897,"t":"מִשָּׁ֜ם","p":"משם","c":12,"v":8},{"id":3898,"t":"הָהָ֗רָה","p":"ההרה","c":12,"v":8},{"id":3899,"t":"מִקֶּ֛דֶם","p":"מקדם","c":12,"v":8},{"id":3900,"t":"לְבֵֽית","p":"לבית","c":12,"v":8},{"id":3901,"t":"אֵ֖ל","p":"אל","c":12,"v":8},{"id":3902,"t":"וַיֵּ֣ט","p":"ויט","c":12,"v":8},{"id":3903,"t":"אׇהֳלֹ֑ה","p":"אהלה","c":12,"v":8},{"id":3904,"t":"בֵּֽית","p":"בית","c":12,"v":8},{"id":3905,"t":"אֵ֤ל","p":"אל","c":12,"v":8},{"id":3906,"t":"מִיָּם֙","p":"מים","c":12,"v":8},{"id":3907,"t":"וְהָעַ֣י","p":"והעי","c":12,"v":8},{"id":3908,"t":"מִקֶּ֔דֶם","p":"מקדם","c":12,"v":8},{"id":3909,"t":"וַיִּֽבֶן","p":"ויבן","c":12,"v":8},{"id":3910,"t":"שָׁ֤ם","p":"שם","c":12,"v":8},{"id":3911,"t":"מִזְבֵּ֙חַ֙","p":"מזבח","c":12,"v":8},{"id":3912,"t":"לַֽיהֹוָ֔ה","p":"ליהוה","c":12,"v":8},{"id":3913,"t":"וַיִּקְרָ֖א","p":"ויקרא","c":12,"v":8},{"id":3914,"t":"בְּשֵׁ֥ם","p":"בשם","c":12,"v":8},{"id":3915,"t":"יְהֹוָֽה","p":"יהוה","c":12,"v":8},{"id":3916,"t":"וַיִּסַּ֣ע","p":"ויסע","c":12,"v":9},{"id":3917,"t":"אַבְרָ֔ם","p":"אברם","c":12,"v":9},{"id":3918,"t":"הָל֥וֹךְ","p":"הלוך","c":12,"v":9},{"id":3919,"t":"וְנָס֖וֹעַ","p":"ונסוע","c":12,"v":9},{"id":3920,"t":"הַנֶּֽגְבָּה","p":"הנגבה","c":12,"v":9},{"id":3921,"t":"וַיְהִ֥י","p":"ויהי","c":12,"v":10},{"id":3922,"t":"רָעָ֖ב","p":"רעב","c":12,"v":10},{"id":3923,"t":"בָּאָ֑רֶץ","p":"בארץ","c":12,"v":10},{"id":3924,"t":"וַיֵּ֨רֶד","p":"וירד","c":12,"v":10},{"id":3925,"t":"אַבְרָ֤ם","p":"אברם","c":12,"v":10},{"id":3926,"t":"מִצְרַ֙יְמָה֙","p":"מצרימה","c":12,"v":10},{"id":3927,"t":"לָג֣וּר","p":"לגור","c":12,"v":10},{"id":3928,"t":"שָׁ֔ם","p":"שם","c":12,"v":10},{"id":3929,"t":"כִּֽי","p":"כי","c":12,"v":10},{"id":3930,"t":"כָבֵ֥ד","p":"כבד","c":12,"v":10},{"id":3931,"t":"הָרָעָ֖ב","p":"הרעב","c":12,"v":10},{"id":3932,"t":"בָּאָֽרֶץ","p":"בארץ","c":12,"v":10},{"id":3933,"t":"וַיְהִ֕י","p":"ויהי","c":12,"v":11},{"id":3934,"t":"כַּאֲשֶׁ֥ר","p":"כאשר","c":12,"v":11},{"id":3935,"t":"הִקְרִ֖יב","p":"הקריב","c":12,"v":11},{"id":3936,"t":"לָב֣וֹא","p":"לבוא","c":12,"v":11},{"id":3937,"t":"מִצְרָ֑יְמָה","p":"מצרימה","c":12,"v":11},{"id":3938,"t":"וַיֹּ֙אמֶר֙","p":"ויאמר","c":12,"v":11},{"id":3939,"t":"אֶל","p":"אל","c":12,"v":11},{"id":3940,"t":"שָׂרַ֣י","p":"שרי","c":12,"v":11},{"id":3941,"t":"אִשְׁתּ֔וֹ","p":"אשתו","c":12,"v":11},{"id":3942,"t":"הִנֵּה","p":"הנה","c":12,"v":11},{"id":3943,"t":"נָ֣א","p":"נא","c":12,"v":11},{"id":3944,"t":"יָדַ֔עְתִּי","p":"ידעתי","c":12,"v":11},{"id":3945,"t":"כִּ֛י","p":"כי","c":12,"v":11},{"id":3946,"t":"אִשָּׁ֥ה","p":"אשה","c":12,"v":11},{"id":3947,"t":"יְפַת","p":"יפת","c":12,"v":11},{"id":3948,"t":"מַרְאֶ֖ה","p":"מראה","c":12,"v":11},{"id":3949,"t":"אָֽתְּ","p":"את","c":12,"v":11},{"id":3950,"t":"וְהָיָ֗ה","p":"והיה","c":12,"v":12},{"id":3951,"t":"כִּֽי","p":"כי","c":12,"v":12},{"id":3952,"t":"יִרְא֤וּ","p":"יראו","c":12,"v":12},{"id":3953,"t":"אֹתָךְ֙","p":"אתך","c":12,"v":12},{"id":3954,"t":"הַמִּצְרִ֔ים","p":"המצרים","c":12,"v":12},{"id":3955,"t":"וְאָמְר֖וּ","p":"ואמרו","c":12,"v":12},{"id":3956,"t":"אִשְׁתּ֣וֹ","p":"אשתו","c":12,"v":12},{"id":3957,"t":"זֹ֑את","p":"זאת","c":12,"v":12},{"id":3958,"t":"וְהָרְג֥וּ","p":"והרגו","c":12,"v":12},{"id":3959,"t":"אֹתִ֖י","p":"אתי","c":12,"v":12},{"id":3960,"t":"וְאֹתָ֥ךְ","p":"ואתך","c":12,"v":12},{"id":3961,"t":"יְחַיּֽוּ","p":"יחיו","c":12,"v":12},{"id":3962,"t":"אִמְרִי","p":"אמרי","c":12,"v":13},{"id":3963,"t":"נָ֖א","p":"נא","c":12,"v":13},{"id":3964,"t":"אֲחֹ֣תִי","p":"אחתי","c":12,"v":13},{"id":3965,"t":"אָ֑תְּ","p":"את","c":12,"v":13},{"id":3966,"t":"לְמַ֙עַן֙","p":"למען","c":12,"v":13},{"id":3967,"t":"יִֽיטַב","p":"ייטב","c":12,"v":13},{"id":3968,"t":"לִ֣י","p":"לי","c":12,"v":13},{"id":3969,"t":"בַעֲבוּרֵ֔ךְ","p":"בעבורך","c":12,"v":13},{"id":3970,"t":"וְחָיְתָ֥ה","p":"וחיתה","c":12,"v":13},{"id":3971,"t":"נַפְשִׁ֖י","p":"נפשי","c":12,"v":13},{"id":3972,"t":"בִּגְלָלֵֽךְ","p":"בגללך","c":12,"v":13},{"id":3973,"t":"וַיְהִ֕י","p":"ויהי","c":12,"v":14},{"id":3974,"t":"כְּב֥וֹא","p":"כבוא","c":12,"v":14},{"id":3975,"t":"אַבְרָ֖ם","p":"אברם","c":12,"v":14},{"id":3976,"t":"מִצְרָ֑יְמָה","p":"מצרימה","c":12,"v":14},{"id":3977,"t":"וַיִּרְא֤וּ","p":"ויראו","c":12,"v":14},{"id":3978,"t":"הַמִּצְרִים֙","p":"המצרים","c":12,"v":14},{"id":3979,"t":"אֶת","p":"את","c":12,"v":14},{"id":3980,"t":"הָ֣אִשָּׁ֔ה","p":"האשה","c":12,"v":14},{"id":3981,"t":"כִּֽי","p":"כי","c":12,"v":14},{"id":3982,"t":"יָפָ֥ה","p":"יפה","c":12,"v":14},{"id":3983,"t":"הִ֖וא","p":"הוא","c":12,"v":14},{"id":3984,"t":"מְאֹֽד","p":"מאד","c":12,"v":14},{"id":3985,"t":"וַיִּרְא֤וּ","p":"ויראו","c":12,"v":15},{"id":3986,"t":"אֹתָהּ֙","p":"אתה","c":12,"v":15},{"id":3987,"t":"שָׂרֵ֣י","p":"שרי","c":12,"v":15},{"id":3988,"t":"פַרְעֹ֔ה","p":"פרעה","c":12,"v":15},{"id":3989,"t":"וַיְהַֽלְל֥וּ","p":"ויהללו","c":12,"v":15},{"id":3990,"t":"אֹתָ֖הּ","p":"אתה","c":12,"v":15},{"id":3991,"t":"אֶל","p":"אל","c":12,"v":15},{"id":3992,"t":"פַּרְעֹ֑ה","p":"פרעה","c":12,"v":15},{"id":3993,"t":"וַתֻּקַּ֥ח","p":"ותקח","c":12,"v":15},{"id":3994,"t":"הָאִשָּׁ֖ה","p":"האשה","c":12,"v":15},{"id":3995,"t":"בֵּ֥ית","p":"בית","c":12,"v":15},{"id":3996,"t":"פַּרְעֹֽה","p":"פרעה","c":12,"v":15},{"id":3997,"t":"וּלְאַבְרָ֥ם","p":"ולאברם","c":12,"v":16},{"id":3998,"t":"הֵיטִ֖יב","p":"היטיב","c":12,"v":16},{"id":3999,"t":"בַּעֲבוּרָ֑הּ","p":"בעבורה","c":12,"v":16},{"id":4000,"t":"וַֽיְהִי","p":"ויהי","c":12,"v":16},{"id":4001,"t":"ל֤וֹ","p":"לו","c":12,"v":16},{"id":4002,"t":"צֹאן","p":"צאן","c":12,"v":16},{"id":4003,"t":"וּבָקָר֙","p":"ובקר","c":12,"v":16},{"id":4004,"t":"וַחֲמֹרִ֔ים","p":"וחמרים","c":12,"v":16},{"id":4005,"t":"וַעֲבָדִים֙","p":"ועבדים","c":12,"v":16},{"id":4006,"t":"וּשְׁפָחֹ֔ת","p":"ושפחת","c":12,"v":16},{"id":4007,"t":"וַאֲתֹנֹ֖ת","p":"ואתנת","c":12,"v":16},{"id":4008,"t":"וּגְמַלִּֽים","p":"וגמלים","c":12,"v":16},{"id":4009,"t":"וַיְנַגַּ֨ע","p":"וינגע","c":12,"v":17},{"id":4010,"t":"יְהֹוָ֧ה","p":"יהוה","c":12,"v":17},{"id":4011,"t":"׀","p":"את","c":12,"v":17},{"id":4012,"t":"אֶת","p":"פרעה","c":12,"v":17},{"id":4013,"t":"פַּרְעֹ֛ה","p":"נגעים","c":12,"v":17},{"id":4014,"t":"נְגָעִ֥ים","p":"גדלים","c":12,"v":17},{"id":4015,"t":"גְּדֹלִ֖ים","p":"ואת","c":12,"v":17},{"id":4016,"t":"וְאֶת","p":"ביתו","c":12,"v":17},{"id":4017,"t":"בֵּית֑וֹ","p":"על","c":12,"v":17},{"id":4018,"t":"עַל","p":"דבר","c":12,"v":17},{"id":4019,"t":"דְּבַ֥ר","p":"שרי","c":12,"v":17},{"id":4020,"t":"שָׂרַ֖י","p":"אשת","c":12,"v":17},{"id":4021,"t":"אֵ֥שֶׁת","p":"אברם","c":12,"v":17},{"id":4022,"t":"וַיִּקְרָ֤א","p":"ויקרא","c":12,"v":18},{"id":4023,"t":"פַרְעֹה֙","p":"פרעה","c":12,"v":18},{"id":4024,"t":"לְאַבְרָ֔ם","p":"לאברם","c":12,"v":18},{"id":4025,"t":"וַיֹּ֕אמֶר","p":"ויאמר","c":12,"v":18},{"id":4026,"t":"מַה","p":"מה","c":12,"v":18},{"id":4027,"t":"זֹּ֖את","p":"זאת","c":12,"v":18},{"id":4028,"t":"עָשִׂ֣יתָ","p":"עשית","c":12,"v":18},{"id":4029,"t":"לִּ֑י","p":"לי","c":12,"v":18},{"id":4030,"t":"לָ֚מָּה","p":"למה","c":12,"v":18},{"id":4031,"t":"לֹא","p":"לא","c":12,"v":18},{"id":4032,"t":"הִגַּ֣דְתָּ","p":"הגדת","c":12,"v":18},{"id":4033,"t":"לִּ֔י","p":"לי","c":12,"v":18},{"id":4034,"t":"כִּ֥י","p":"כי","c":12,"v":18},{"id":4035,"t":"אִשְׁתְּךָ֖","p":"אשתך","c":12,"v":18},{"id":4036,"t":"הִֽוא","p":"הוא","c":12,"v":18},{"id":4037,"t":"לָמָ֤ה","p":"למה","c":12,"v":19},{"id":4038,"t":"אָמַ֙רְתָּ֙","p":"אמרת","c":12,"v":19},{"id":4039,"t":"אֲחֹ֣תִי","p":"אחתי","c":12,"v":19},{"id":4040,"t":"הִ֔וא","p":"הוא","c":12,"v":19},{"id":4041,"t":"וָאֶקַּ֥ח","p":"ואקח","c":12,"v":19},{"id":4042,"t":"אֹתָ֛הּ","p":"אתה","c":12,"v":19},{"id":4043,"t":"לִ֖י","p":"לי","c":12,"v":19},{"id":4044,"t":"לְאִשָּׁ֑ה","p":"לאשה","c":12,"v":19},{"id":4045,"t":"וְעַתָּ֕ה","p":"ועתה","c":12,"v":19},{"id":4046,"t":"הִנֵּ֥ה","p":"הנה","c":12,"v":19},{"id":4047,"t":"אִשְׁתְּךָ֖","p":"אשתך","c":12,"v":19},{"id":4048,"t":"קַ֥ח","p":"קח","c":12,"v":19},{"id":4049,"t":"וָלֵֽךְ","p":"ולך","c":12,"v":19},{"id":4050,"t":"וַיְצַ֥ו","p":"ויצו","c":12,"v":20},{"id":4051,"t":"עָלָ֛יו","p":"עליו","c":12,"v":20},{"id":4052,"t":"פַּרְעֹ֖ה","p":"פרעה","c":12,"v":20},{"id":4053,"t":"אֲנָשִׁ֑ים","p":"אנשים","c":12,"v":20},{"id":4054,"t":"וַֽיְשַׁלְּח֥וּ","p":"וישלחו","c":12,"v":20},{"id":4055,"t":"אֹת֛וֹ","p":"אתו","c":12,"v":20},{"id":4056,"t":"וְאֶת","p":"ואת","c":12,"v":20},{"id":4057,"t":"אִשְׁתּ֖וֹ","p":"אשתו","c":12,"v":20},{"id":4058,"t":"וְאֶת","p":"ואת","c":12,"v":20},{"id":4059,"t":"כׇּל","p":"כל","c":12,"v":20},{"id":4060,"t":"אֲשֶׁר","p":"אשר","c":12,"v":20},{"id":4061,"t":"לֽוֹ","p":"לו","c":12,"v":20},{"id":4062,"t":"וַיַּ֩עַל֩","p":"ויעל","c":13,"v":1},{"id":4063,"t":"אַבְרָ֨ם","p":"אברם","c":13,"v":1},{"id":4064,"t":"מִמִּצְרַ֜יִם","p":"ממצרים","c":13,"v":1},{"id":4065,"t":"ה֠וּא","p":"הוא","c":13,"v":1},{"id":4066,"t":"וְאִשְׁתּ֧וֹ","p":"ואשתו","c":13,"v":1},{"id":4067,"t":"וְכׇל","p":"וכל","c":13,"v":1},{"id":4068,"t":"אֲשֶׁר","p":"אשר","c":13,"v":1},{"id":4069,"t":"ל֛וֹ","p":"לו","c":13,"v":1},{"id":4070,"t":"וְל֥וֹט","p":"ולוט","c":13,"v":1},{"id":4071,"t":"עִמּ֖וֹ","p":"עמו","c":13,"v":1},{"id":4072,"t":"הַנֶּֽגְבָּה","p":"הנגבה","c":13,"v":1},{"id":4073,"t":"וְאַבְרָ֖ם","p":"ואברם","c":13,"v":2},{"id":4074,"t":"כָּבֵ֣ד","p":"כבד","c":13,"v":2},{"id":4075,"t":"מְאֹ֑ד","p":"מאד","c":13,"v":2},{"id":4076,"t":"בַּמִּקְנֶ֕ה","p":"במקנה","c":13,"v":2},{"id":4077,"t":"בַּכֶּ֖סֶף","p":"בכסף","c":13,"v":2},{"id":4078,"t":"וּבַזָּהָֽב","p":"ובזהב","c":13,"v":2},{"id":4079,"t":"וַיֵּ֙לֶךְ֙","p":"וילך","c":13,"v":3},{"id":4080,"t":"לְמַסָּעָ֔יו","p":"למסעיו","c":13,"v":3},{"id":4081,"t":"מִנֶּ֖גֶב","p":"מנגב","c":13,"v":3},{"id":4082,"t":"וְעַד","p":"ועד","c":13,"v":3},{"id":4083,"t":"בֵּֽית","p":"בית","c":13,"v":3},{"id":4084,"t":"אֵ֑ל","p":"אל","c":13,"v":3},{"id":4085,"t":"עַד","p":"עד","c":13,"v":3},{"id":4086,"t":"הַמָּק֗וֹם","p":"המקום","c":13,"v":3},{"id":4087,"t":"אֲשֶׁר","p":"אשר","c":13,"v":3},{"id":4088,"t":"הָ֨יָה","p":"היה","c":13,"v":3},{"id":4089,"t":"שָׁ֤ם","p":"שם","c":13,"v":3},{"id":4090,"t":"אׇֽהֳלֹה֙","p":"אהלה","c":13,"v":3},{"id":4091,"t":"בַּתְּחִלָּ֔ה","p":"אהלו","c":13,"v":3},{"id":4092,"t":"בֵּ֥ין","p":"בתחלה","c":13,"v":3},{"id":4093,"t":"בֵּֽית","p":"בין","c":13,"v":3},{"id":4094,"t":"אֵ֖ל","p":"בית","c":13,"v":3},{"id":4095,"t":"וּבֵ֥ין","p":"אל","c":13,"v":3},{"id":4096,"t":"הָעָֽי","p":"ובין","c":13,"v":3},{"id":4097,"t":"העי","p":"העי","c":13,"v":3},{"id":4098,"t":"אֶל","p":"אל","c":13,"v":4},{"id":4099,"t":"מְקוֹם֙","p":"מקום","c":13,"v":4},{"id":4100,"t":"הַמִּזְבֵּ֔חַ","p":"המזבח","c":13,"v":4},{"id":4101,"t":"אֲשֶׁר","p":"אשר","c":13,"v":4},{"id":4102,"t":"עָ֥שָׂה","p":"עשה","c":13,"v":4},{"id":4103,"t":"שָׁ֖ם","p":"שם","c":13,"v":4},{"id":4104,"t":"בָּרִאשֹׁנָ֑ה","p":"בראשנה","c":13,"v":4},{"id":4105,"t":"וַיִּקְרָ֥א","p":"ויקרא","c":13,"v":4},{"id":4106,"t":"שָׁ֛ם","p":"שם","c":13,"v":4},{"id":4107,"t":"אַבְרָ֖ם","p":"אברם","c":13,"v":4},{"id":4108,"t":"בְּשֵׁ֥ם","p":"בשם","c":13,"v":4},{"id":4109,"t":"יְהֹוָֽה","p":"יהוה","c":13,"v":4},{"id":4110,"t":"וְגַ֨ם","p":"וגם","c":13,"v":5},{"id":4111,"t":"לְל֔וֹט","p":"ללוט","c":13,"v":5},{"id":4112,"t":"הַהֹלֵ֖ךְ","p":"ההלך","c":13,"v":5},{"id":4113,"t":"אֶת","p":"את","c":13,"v":5},{"id":4114,"t":"אַבְרָ֑ם","p":"אברם","c":13,"v":5},{"id":4115,"t":"הָיָ֥ה","p":"היה","c":13,"v":5},{"id":4116,"t":"צֹאן","p":"צאן","c":13,"v":5},{"id":4117,"t":"וּבָקָ֖ר","p":"ובקר","c":13,"v":5},{"id":4118,"t":"וְאֹהָלִֽים","p":"ואהלים","c":13,"v":5},{"id":4119,"t":"וְלֹא","p":"ולא","c":13,"v":6},{"id":4120,"t":"נָשָׂ֥א","p":"נשא","c":13,"v":6},{"id":4121,"t":"אֹתָ֛ם","p":"אתם","c":13,"v":6},{"id":4122,"t":"הָאָ֖רֶץ","p":"הארץ","c":13,"v":6},{"id":4123,"t":"לָשֶׁ֣בֶת","p":"לשבת","c":13,"v":6},{"id":4124,"t":"יַחְדָּ֑ו","p":"יחדו","c":13,"v":6},{"id":4125,"t":"כִּֽי","p":"כי","c":13,"v":6},{"id":4126,"t":"הָיָ֤ה","p":"היה","c":13,"v":6},{"id":4127,"t":"רְכוּשָׁם֙","p":"רכושם","c":13,"v":6},{"id":4128,"t":"רָ֔ב","p":"רב","c":13,"v":6},{"id":4129,"t":"וְלֹ֥א","p":"ולא","c":13,"v":6},{"id":4130,"t":"יָֽכְל֖וּ","p":"יכלו","c":13,"v":6},{"id":4131,"t":"לָשֶׁ֥בֶת","p":"לשבת","c":13,"v":6},{"id":4132,"t":"יַחְדָּֽו","p":"יחדו","c":13,"v":6},{"id":4133,"t":"וַֽיְהִי","p":"ויהי","c":13,"v":7},{"id":4134,"t":"רִ֗יב","p":"ריב","c":13,"v":7},{"id":4135,"t":"בֵּ֚ין","p":"בין","c":13,"v":7},{"id":4136,"t":"רֹעֵ֣י","p":"רעי","c":13,"v":7},{"id":4137,"t":"מִקְנֵֽה","p":"מקנה","c":13,"v":7},{"id":4138,"t":"אַבְרָ֔ם","p":"אברם","c":13,"v":7},{"id":4139,"t":"וּבֵ֖ין","p":"ובין","c":13,"v":7},{"id":4140,"t":"רֹעֵ֣י","p":"רעי","c":13,"v":7},{"id":4141,"t":"מִקְנֵה","p":"מקנה","c":13,"v":7},{"id":4142,"t":"ל֑וֹט","p":"לוט","c":13,"v":7},{"id":4143,"t":"וְהַֽכְּנַעֲנִי֙","p":"והכנעני","c":13,"v":7},{"id":4144,"t":"וְהַפְּרִזִּ֔י","p":"והפרזי","c":13,"v":7},{"id":4145,"t":"אָ֖ז","p":"אז","c":13,"v":7},{"id":4146,"t":"יֹשֵׁ֥ב","p":"ישב","c":13,"v":7},{"id":4147,"t":"בָּאָֽרֶץ","p":"בארץ","c":13,"v":7},{"id":4148,"t":"וַיֹּ֨אמֶר","p":"ויאמר","c":13,"v":8},{"id":4149,"t":"אַבְרָ֜ם","p":"אברם","c":13,"v":8},{"id":4150,"t":"אֶל","p":"אל","c":13,"v":8},{"id":4151,"t":"ל֗וֹט","p":"לוט","c":13,"v":8},{"id":4152,"t":"אַל","p":"אל","c":13,"v":8},{"id":4153,"t":"נָ֨א","p":"נא","c":13,"v":8},{"id":4154,"t":"תְהִ֤י","p":"תהי","c":13,"v":8},{"id":4155,"t":"מְרִיבָה֙","p":"מריבה","c":13,"v":8},{"id":4156,"t":"בֵּינִ֣י","p":"ביני","c":13,"v":8},{"id":4157,"t":"וּבֵינֶ֔ךָ","p":"וביניך","c":13,"v":8},{"id":4158,"t":"וּבֵ֥ין","p":"ובין","c":13,"v":8},{"id":4159,"t":"רֹעַ֖י","p":"רעי","c":13,"v":8},{"id":4160,"t":"וּבֵ֣ין","p":"ובין","c":13,"v":8},{"id":4161,"t":"רֹעֶ֑יךָ","p":"רעיך","c":13,"v":8},{"id":4162,"t":"כִּֽי","p":"כי","c":13,"v":8},{"id":4163,"t":"אֲנָשִׁ֥ים","p":"אנשים","c":13,"v":8},{"id":4164,"t":"אַחִ֖ים","p":"אחים","c":13,"v":8},{"id":4165,"t":"אֲנָֽחְנוּ","p":"אנחנו","c":13,"v":8},{"id":4166,"t":"הֲלֹ֤א","p":"הלא","c":13,"v":9},{"id":4167,"t":"כׇל","p":"כל","c":13,"v":9},{"id":4168,"t":"הָאָ֙רֶץ֙","p":"הארץ","c":13,"v":9},{"id":4169,"t":"לְפָנֶ֔יךָ","p":"לפניך","c":13,"v":9},{"id":4170,"t":"הִפָּ֥רֶד","p":"הפרד","c":13,"v":9},{"id":4171,"t":"נָ֖א","p":"נא","c":13,"v":9},{"id":4172,"t":"מֵעָלָ֑י","p":"מעלי","c":13,"v":9},{"id":4173,"t":"אִם","p":"אם","c":13,"v":9},{"id":4174,"t":"הַשְּׂמֹ֣אל","p":"השמאל","c":13,"v":9},{"id":4175,"t":"וְאֵימִ֔נָה","p":"ואימנה","c":13,"v":9},{"id":4176,"t":"וְאִם","p":"ואם","c":13,"v":9},{"id":4177,"t":"הַיָּמִ֖ין","p":"הימין","c":13,"v":9},{"id":4178,"t":"וְאַשְׂמְאִֽילָה","p":"ואשמאילה","c":13,"v":9},{"id":4179,"t":"וַיִּשָּׂא","p":"וישא","c":13,"v":10},{"id":4180,"t":"ל֣וֹט","p":"לוט","c":13,"v":10},{"id":4181,"t":"אֶת","p":"את","c":13,"v":10},{"id":4182,"t":"עֵינָ֗יו","p":"עיניו","c":13,"v":10},{"id":4183,"t":"וַיַּרְא֙","p":"וירא","c":13,"v":10},{"id":4184,"t":"אֶת","p":"את","c":13,"v":10},{"id":4185,"t":"כׇּל","p":"כל","c":13,"v":10},{"id":4186,"t":"כִּכַּ֣ר","p":"ככר","c":13,"v":10},{"id":4187,"t":"הַיַּרְדֵּ֔ן","p":"הירדן","c":13,"v":10},{"id":4188,"t":"כִּ֥י","p":"כי","c":13,"v":10},{"id":4189,"t":"כֻלָּ֖הּ","p":"כלה","c":13,"v":10},{"id":4190,"t":"מַשְׁקֶ֑ה","p":"משקה","c":13,"v":10},{"id":4191,"t":"לִפְנֵ֣י","p":"לפני","c":13,"v":10},{"id":4192,"t":"׀","p":"שחת","c":13,"v":10},{"id":4193,"t":"שַׁחֵ֣ת","p":"יהוה","c":13,"v":10},{"id":4194,"t":"יְהֹוָ֗ה","p":"את","c":13,"v":10},{"id":4195,"t":"אֶת","p":"סדם","c":13,"v":10},{"id":4196,"t":"סְדֹם֙","p":"ואת","c":13,"v":10},{"id":4197,"t":"וְאֶת","p":"עמרה","c":13,"v":10},{"id":4198,"t":"עֲמֹרָ֔ה","p":"כגן","c":13,"v":10},{"id":4199,"t":"כְּגַן","p":"יהוה","c":13,"v":10},{"id":4200,"t":"יְהֹוָה֙","p":"כארץ","c":13,"v":10},{"id":4201,"t":"כְּאֶ֣רֶץ","p":"מצרים","c":13,"v":10},{"id":4202,"t":"מִצְרַ֔יִם","p":"באכה","c":13,"v":10},{"id":4203,"t":"בֹּאֲכָ֖ה","p":"צער","c":13,"v":10},{"id":4204,"t":"וַיִּבְחַר","p":"ויבחר","c":13,"v":11},{"id":4205,"t":"ל֣וֹ","p":"לו","c":13,"v":11},{"id":4206,"t":"ל֗וֹט","p":"לוט","c":13,"v":11},{"id":4207,"t":"אֵ֚ת","p":"את","c":13,"v":11},{"id":4208,"t":"כׇּל","p":"כל","c":13,"v":11},{"id":4209,"t":"כִּכַּ֣ר","p":"ככר","c":13,"v":11},{"id":4210,"t":"הַיַּרְדֵּ֔ן","p":"הירדן","c":13,"v":11},{"id":4211,"t":"וַיִּסַּ֥ע","p":"ויסע","c":13,"v":11},{"id":4212,"t":"ל֖וֹט","p":"לוט","c":13,"v":11},{"id":4213,"t":"מִקֶּ֑דֶם","p":"מקדם","c":13,"v":11},{"id":4214,"t":"וַיִּפָּ֣רְד֔וּ","p":"ויפרדו","c":13,"v":11},{"id":4215,"t":"אִ֖ישׁ","p":"איש","c":13,"v":11},{"id":4216,"t":"מֵעַ֥ל","p":"מעל","c":13,"v":11},{"id":4217,"t":"אָחִֽיו","p":"אחיו","c":13,"v":11},{"id":4218,"t":"אַבְרָ֖ם","p":"אברם","c":13,"v":12},{"id":4219,"t":"יָשַׁ֣ב","p":"ישב","c":13,"v":12},{"id":4220,"t":"בְּאֶֽרֶץ","p":"בארץ","c":13,"v":12},{"id":4221,"t":"כְּנָ֑עַן","p":"כנען","c":13,"v":12},{"id":4222,"t":"וְל֗וֹט","p":"ולוט","c":13,"v":12},{"id":4223,"t":"יָשַׁב֙","p":"ישב","c":13,"v":12},{"id":4224,"t":"בְּעָרֵ֣י","p":"בערי","c":13,"v":12},{"id":4225,"t":"הַכִּכָּ֔ר","p":"הככר","c":13,"v":12},{"id":4226,"t":"וַיֶּאֱהַ֖ל","p":"ויאהל","c":13,"v":12},{"id":4227,"t":"עַד","p":"עד","c":13,"v":12},{"id":4228,"t":"סְדֹֽם","p":"סדם","c":13,"v":12},{"id":4229,"t":"וְאַנְשֵׁ֣י","p":"ואנשי","c":13,"v":13},{"id":4230,"t":"סְדֹ֔ם","p":"סדם","c":13,"v":13},{"id":4231,"t":"רָעִ֖ים","p":"רעים","c":13,"v":13},{"id":4232,"t":"וְחַטָּאִ֑ים","p":"וחטאים","c":13,"v":13},{"id":4233,"t":"לַיהֹוָ֖ה","p":"ליהוה","c":13,"v":13},{"id":4234,"t":"מְאֹֽד","p":"מאד","c":13,"v":13},{"id":4235,"t":"וַֽיהֹוָ֞ה","p":"ויהוה","c":13,"v":14},{"id":4236,"t":"אָמַ֣ר","p":"אמר","c":13,"v":14},{"id":4237,"t":"אֶל","p":"אל","c":13,"v":14},{"id":4238,"t":"אַבְרָ֗ם","p":"אברם","c":13,"v":14},{"id":4239,"t":"אַחֲרֵי֙","p":"אחרי","c":13,"v":14},{"id":4240,"t":"הִפָּֽרֶד","p":"הפרד","c":13,"v":14},{"id":4241,"t":"ל֣וֹט","p":"לוט","c":13,"v":14},{"id":4242,"t":"מֵֽעִמּ֔וֹ","p":"מעמו","c":13,"v":14},{"id":4243,"t":"שָׂ֣א","p":"שא","c":13,"v":14},{"id":4244,"t":"נָ֤א","p":"נא","c":13,"v":14},{"id":4245,"t":"עֵינֶ֙יךָ֙","p":"עיניך","c":13,"v":14},{"id":4246,"t":"וּרְאֵ֔ה","p":"וראה","c":13,"v":14},{"id":4247,"t":"מִן","p":"מן","c":13,"v":14},{"id":4248,"t":"הַמָּק֖וֹם","p":"המקום","c":13,"v":14},{"id":4249,"t":"אֲשֶׁר","p":"אשר","c":13,"v":14},{"id":4250,"t":"אַתָּ֣ה","p":"אתה","c":13,"v":14},{"id":4251,"t":"שָׁ֑ם","p":"שם","c":13,"v":14},{"id":4252,"t":"צָפֹ֥נָה","p":"צפנה","c":13,"v":14},{"id":4253,"t":"וָנֶ֖גְבָּה","p":"ונגבה","c":13,"v":14},{"id":4254,"t":"וָקֵ֥דְמָה","p":"וקדמה","c":13,"v":14},{"id":4255,"t":"וָיָֽמָּה","p":"וימה","c":13,"v":14},{"id":4256,"t":"כִּ֧י","p":"כי","c":13,"v":15},{"id":4257,"t":"אֶת","p":"את","c":13,"v":15},{"id":4258,"t":"כׇּל","p":"כל","c":13,"v":15},{"id":4259,"t":"הָאָ֛רֶץ","p":"הארץ","c":13,"v":15},{"id":4260,"t":"אֲשֶׁר","p":"אשר","c":13,"v":15},{"id":4261,"t":"אַתָּ֥ה","p":"אתה","c":13,"v":15},{"id":4262,"t":"רֹאֶ֖ה","p":"ראה","c":13,"v":15},{"id":4263,"t":"לְךָ֣","p":"לך","c":13,"v":15},{"id":4264,"t":"אֶתְּנֶ֑נָּה","p":"אתננה","c":13,"v":15},{"id":4265,"t":"וּֽלְזַרְעֲךָ֖","p":"ולזרעך","c":13,"v":15},{"id":4266,"t":"עַד","p":"עד","c":13,"v":15},{"id":4267,"t":"עוֹלָֽם","p":"עולם","c":13,"v":15},{"id":4268,"t":"וְשַׂמְתִּ֥י","p":"ושמתי","c":13,"v":16},{"id":4269,"t":"אֶֽת","p":"את","c":13,"v":16},{"id":4270,"t":"זַרְעֲךָ֖","p":"זרעך","c":13,"v":16},{"id":4271,"t":"כַּעֲפַ֣ר","p":"כעפר","c":13,"v":16},{"id":4272,"t":"הָאָ֑רֶץ","p":"הארץ","c":13,"v":16},{"id":4273,"t":"אֲשֶׁ֣ר","p":"אשר","c":13,"v":16},{"id":4274,"t":"׀","p":"אם","c":13,"v":16},{"id":4275,"t":"אִם","p":"יוכל","c":13,"v":16},{"id":4276,"t":"יוּכַ֣ל","p":"איש","c":13,"v":16},{"id":4277,"t":"אִ֗ישׁ","p":"למנות","c":13,"v":16},{"id":4278,"t":"לִמְנוֹת֙","p":"את","c":13,"v":16},{"id":4279,"t":"אֶת","p":"עפר","c":13,"v":16},{"id":4280,"t":"עֲפַ֣ר","p":"הארץ","c":13,"v":16},{"id":4281,"t":"הָאָ֔רֶץ","p":"גם","c":13,"v":16},{"id":4282,"t":"גַּֽם","p":"זרעך","c":13,"v":16},{"id":4283,"t":"זַרְעֲךָ֖","p":"ימנה","c":13,"v":16},{"id":4284,"t":"ק֚וּם","p":"קום","c":13,"v":17},{"id":4285,"t":"הִתְהַלֵּ֣ךְ","p":"התהלך","c":13,"v":17},{"id":4286,"t":"בָּאָ֔רֶץ","p":"בארץ","c":13,"v":17},{"id":4287,"t":"לְאׇרְכָּ֖הּ","p":"לארכה","c":13,"v":17},{"id":4288,"t":"וּלְרׇחְבָּ֑הּ","p":"ולרחבה","c":13,"v":17},{"id":4289,"t":"כִּ֥י","p":"כי","c":13,"v":17},{"id":4290,"t":"לְךָ֖","p":"לך","c":13,"v":17},{"id":4291,"t":"אֶתְּנֶֽנָּה","p":"אתננה","c":13,"v":17},{"id":4292,"t":"וַיֶּאֱהַ֣ל","p":"ויאהל","c":13,"v":18},{"id":4293,"t":"אַבְרָ֗ם","p":"אברם","c":13,"v":18},{"id":4294,"t":"וַיָּבֹ֛א","p":"ויבא","c":13,"v":18},{"id":4295,"t":"וַיֵּ֛שֶׁב","p":"וישב","c":13,"v":18},{"id":4296,"t":"בְּאֵלֹנֵ֥י","p":"באלני","c":13,"v":18},{"id":4297,"t":"מַמְרֵ֖א","p":"ממרא","c":13,"v":18},{"id":4298,"t":"אֲשֶׁ֣ר","p":"אשר","c":13,"v":18},{"id":4299,"t":"בְּחֶבְר֑וֹן","p":"בחברון","c":13,"v":18},{"id":4300,"t":"וַיִּֽבֶן","p":"ויבן","c":13,"v":18},{"id":4301,"t":"שָׁ֥ם","p":"שם","c":13,"v":18},{"id":4302,"t":"מִזְבֵּ֖חַ","p":"מזבח","c":13,"v":18},{"id":4303,"t":"לַֽיהֹוָֽה","p":"ליהוה","c":13,"v":18},{"id":4304,"t":"וַיְהִ֗י","p":"ויהי","c":14,"v":1},{"id":4305,"t":"בִּימֵי֙","p":"בימי","c":14,"v":1},{"id":4306,"t":"אַמְרָפֶ֣ל","p":"אמרפל","c":14,"v":1},{"id":4307,"t":"מֶֽלֶךְ","p":"מלך","c":14,"v":1},{"id":4308,"t":"שִׁנְעָ֔ר","p":"שנער","c":14,"v":1},{"id":4309,"t":"אַרְי֖וֹךְ","p":"אריוך","c":14,"v":1},{"id":4310,"t":"מֶ֣לֶךְ","p":"מלך","c":14,"v":1},{"id":4311,"t":"אֶלָּסָ֑ר","p":"אלסר","c":14,"v":1},{"id":4312,"t":"כְּדׇרְלָעֹ֙מֶר֙","p":"כדרלעמר","c":14,"v":1},{"id":4313,"t":"מֶ֣לֶךְ","p":"מלך","c":14,"v":1},{"id":4314,"t":"עֵילָ֔ם","p":"עילם","c":14,"v":1},{"id":4315,"t":"וְתִדְעָ֖ל","p":"ותדעל","c":14,"v":1},{"id":4316,"t":"מֶ֥לֶךְ","p":"מלך","c":14,"v":1},{"id":4317,"t":"גּוֹיִֽם","p":"גוים","c":14,"v":1},{"id":4318,"t":"עָשׂ֣וּ","p":"עשו","c":14,"v":2},{"id":4319,"t":"מִלְחָמָ֗ה","p":"מלחמה","c":14,"v":2},{"id":4320,"t":"אֶת","p":"את","c":14,"v":2},{"id":4321,"t":"בֶּ֙רַע֙","p":"ברע","c":14,"v":2},{"id":4322,"t":"מֶ֣לֶךְ","p":"מלך","c":14,"v":2},{"id":4323,"t":"סְדֹ֔ם","p":"סדם","c":14,"v":2},{"id":4324,"t":"וְאֶת","p":"ואת","c":14,"v":2},{"id":4325,"t":"בִּרְשַׁ֖ע","p":"ברשע","c":14,"v":2},{"id":4326,"t":"מֶ֣לֶךְ","p":"מלך","c":14,"v":2},{"id":4327,"t":"עֲמֹרָ֑ה","p":"עמרה","c":14,"v":2},{"id":4328,"t":"שִׁנְאָ֣ב","p":"שנאב","c":14,"v":2},{"id":4329,"t":"׀","p":"מלך","c":14,"v":2},{"id":4330,"t":"מֶ֣לֶךְ","p":"אדמה","c":14,"v":2},{"id":4331,"t":"אַדְמָ֗ה","p":"ושמאבר","c":14,"v":2},{"id":4332,"t":"וְשֶׁמְאֵ֙בֶר֙","p":"מלך","c":14,"v":2},{"id":4333,"t":"מֶ֣לֶךְ","p":"צביים","c":14,"v":2},{"id":4334,"t":"צביים","p":"צבויים","c":14,"v":2},{"id":4335,"t":"צְבוֹיִ֔ם","p":"ומלך","c":14,"v":2},{"id":4336,"t":"וּמֶ֥לֶךְ","p":"בלע","c":14,"v":2},{"id":4337,"t":"בֶּ֖לַע","p":"היא","c":14,"v":2},{"id":4338,"t":"הִיא","p":"צער","c":14,"v":2},{"id":4339,"t":"כׇּל","p":"כל","c":14,"v":3},{"id":4340,"t":"אֵ֙לֶּה֙","p":"אלה","c":14,"v":3},{"id":4341,"t":"חָֽבְר֔וּ","p":"חברו","c":14,"v":3},{"id":4342,"t":"אֶל","p":"אל","c":14,"v":3},{"id":4343,"t":"עֵ֖מֶק","p":"עמק","c":14,"v":3},{"id":4344,"t":"הַשִּׂדִּ֑ים","p":"השדים","c":14,"v":3},{"id":4345,"t":"ה֖וּא","p":"הוא","c":14,"v":3},{"id":4346,"t":"יָ֥ם","p":"ים","c":14,"v":3},{"id":4347,"t":"הַמֶּֽלַח","p":"המלח","c":14,"v":3},{"id":4348,"t":"שְׁתֵּ֤ים","p":"שתים","c":14,"v":4},{"id":4349,"t":"עֶשְׂרֵה֙","p":"עשרה","c":14,"v":4},{"id":4350,"t":"שָׁנָ֔ה","p":"שנה","c":14,"v":4},{"id":4351,"t":"עָבְד֖וּ","p":"עבדו","c":14,"v":4},{"id":4352,"t":"אֶת","p":"את","c":14,"v":4},{"id":4353,"t":"כְּדׇרְלָעֹ֑מֶר","p":"כדרלעמר","c":14,"v":4},{"id":4354,"t":"וּשְׁלֹשׁ","p":"ושלש","c":14,"v":4},{"id":4355,"t":"עֶשְׂרֵ֥ה","p":"עשרה","c":14,"v":4},{"id":4356,"t":"שָׁנָ֖ה","p":"שנה","c":14,"v":4},{"id":4357,"t":"מָרָֽדוּ","p":"מרדו","c":14,"v":4},{"id":4358,"t":"וּבְאַרְבַּע֩","p":"ובארבע","c":14,"v":5},{"id":4359,"t":"עֶשְׂרֵ֨ה","p":"עשרה","c":14,"v":5},{"id":4360,"t":"שָׁנָ֜ה","p":"שנה","c":14,"v":5},{"id":4361,"t":"בָּ֣א","p":"בא","c":14,"v":5},{"id":4362,"t":"כְדׇרְלָעֹ֗מֶר","p":"כדרלעמר","c":14,"v":5},{"id":4363,"t":"וְהַמְּלָכִים֙","p":"והמלכים","c":14,"v":5},{"id":4364,"t":"אֲשֶׁ֣ר","p":"אשר","c":14,"v":5},{"id":4365,"t":"אִתּ֔וֹ","p":"אתו","c":14,"v":5},{"id":4366,"t":"וַיַּכּ֤וּ","p":"ויכו","c":14,"v":5},{"id":4367,"t":"אֶת","p":"את","c":14,"v":5},{"id":4368,"t":"רְפָאִים֙","p":"רפאים","c":14,"v":5},{"id":4369,"t":"בְּעַשְׁתְּרֹ֣ת","p":"בעשתרת","c":14,"v":5},{"id":4370,"t":"קַרְנַ֔יִם","p":"קרנים","c":14,"v":5},{"id":4371,"t":"וְאֶת","p":"ואת","c":14,"v":5},{"id":4372,"t":"הַזּוּזִ֖ים","p":"הזוזים","c":14,"v":5},{"id":4373,"t":"בְּהָ֑ם","p":"בהם","c":14,"v":5},{"id":4374,"t":"וְאֵת֙","p":"ואת","c":14,"v":5},{"id":4375,"t":"הָֽאֵימִ֔ים","p":"האימים","c":14,"v":5},{"id":4376,"t":"בְּשָׁוֵ֖ה","p":"בשוה","c":14,"v":5},{"id":4377,"t":"קִרְיָתָֽיִם","p":"קריתים","c":14,"v":5},{"id":4378,"t":"וְאֶת","p":"ואת","c":14,"v":6},{"id":4379,"t":"הַחֹרִ֖י","p":"החרי","c":14,"v":6},{"id":4380,"t":"בְּהַרְרָ֣ם","p":"בהררם","c":14,"v":6},{"id":4381,"t":"שֵׂעִ֑יר","p":"שעיר","c":14,"v":6},{"id":4382,"t":"עַ֚ד","p":"עד","c":14,"v":6},{"id":4383,"t":"אֵ֣יל","p":"איל","c":14,"v":6},{"id":4384,"t":"פָּארָ֔ן","p":"פארן","c":14,"v":6},{"id":4385,"t":"אֲשֶׁ֖ר","p":"אשר","c":14,"v":6},{"id":4386,"t":"עַל","p":"על","c":14,"v":6},{"id":4387,"t":"הַמִּדְבָּֽר","p":"המדבר","c":14,"v":6},{"id":4388,"t":"וַ֠יָּשֻׁ֠בוּ","p":"וישבו","c":14,"v":7},{"id":4389,"t":"וַיָּבֹ֜אוּ","p":"ויבאו","c":14,"v":7},{"id":4390,"t":"אֶל","p":"אל","c":14,"v":7},{"id":4391,"t":"עֵ֤ין","p":"עין","c":14,"v":7},{"id":4392,"t":"מִשְׁפָּט֙","p":"משפט","c":14,"v":7},{"id":4393,"t":"הִ֣וא","p":"הוא","c":14,"v":7},{"id":4394,"t":"קָדֵ֔שׁ","p":"קדש","c":14,"v":7},{"id":4395,"t":"וַיַּכּ֕וּ","p":"ויכו","c":14,"v":7},{"id":4396,"t":"אֶֽת","p":"את","c":14,"v":7},{"id":4397,"t":"כׇּל","p":"כל","c":14,"v":7},{"id":4398,"t":"שְׂדֵ֖ה","p":"שדה","c":14,"v":7},{"id":4399,"t":"הָעֲמָלֵקִ֑י","p":"העמלקי","c":14,"v":7},{"id":4400,"t":"וְגַם֙","p":"וגם","c":14,"v":7},{"id":4401,"t":"אֶת","p":"את","c":14,"v":7},{"id":4402,"t":"הָ֣אֱמֹרִ֔י","p":"האמרי","c":14,"v":7},{"id":4403,"t":"הַיֹּשֵׁ֖ב","p":"הישב","c":14,"v":7},{"id":4404,"t":"בְּחַֽצְצֹ֥ן","p":"בחצצן","c":14,"v":7},{"id":4405,"t":"תָּמָֽר","p":"תמר","c":14,"v":7},{"id":4406,"t":"וַיֵּצֵ֨א","p":"ויצא","c":14,"v":8},{"id":4407,"t":"מֶֽלֶךְ","p":"מלך","c":14,"v":8},{"id":4408,"t":"סְדֹ֜ם","p":"סדם","c":14,"v":8},{"id":4409,"t":"וּמֶ֣לֶךְ","p":"ומלך","c":14,"v":8},{"id":4410,"t":"עֲמֹרָ֗ה","p":"עמרה","c":14,"v":8},{"id":4411,"t":"וּמֶ֤לֶךְ","p":"ומלך","c":14,"v":8},{"id":4412,"t":"אַדְמָה֙","p":"אדמה","c":14,"v":8},{"id":4413,"t":"וּמֶ֣לֶךְ","p":"ומלך","c":14,"v":8},{"id":4414,"t":"צביים","p":"צביים","c":14,"v":8},{"id":4415,"t":"צְבוֹיִ֔ם","p":"צבוים","c":14,"v":8},{"id":4416,"t":"וּמֶ֥לֶךְ","p":"ומלך","c":14,"v":8},{"id":4417,"t":"בֶּ֖לַע","p":"בלע","c":14,"v":8},{"id":4418,"t":"הִוא","p":"הוא","c":14,"v":8},{"id":4419,"t":"צֹ֑עַר","p":"צער","c":14,"v":8},{"id":4420,"t":"וַיַּֽעַרְכ֤וּ","p":"ויערכו","c":14,"v":8},{"id":4421,"t":"אִתָּם֙","p":"אתם","c":14,"v":8},{"id":4422,"t":"מִלְחָמָ֔ה","p":"מלחמה","c":14,"v":8},{"id":4423,"t":"בְּעֵ֖מֶק","p":"בעמק","c":14,"v":8},{"id":4424,"t":"הַשִּׂדִּֽים","p":"השדים","c":14,"v":8},{"id":4425,"t":"אֵ֣ת","p":"את","c":14,"v":9},{"id":4426,"t":"כְּדׇרְלָעֹ֜מֶר","p":"כדרלעמר","c":14,"v":9},{"id":4427,"t":"מֶ֣לֶךְ","p":"מלך","c":14,"v":9},{"id":4428,"t":"עֵילָ֗ם","p":"עילם","c":14,"v":9},{"id":4429,"t":"וְתִדְעָל֙","p":"ותדעל","c":14,"v":9},{"id":4430,"t":"מֶ֣לֶךְ","p":"מלך","c":14,"v":9},{"id":4431,"t":"גּוֹיִ֔ם","p":"גוים","c":14,"v":9},{"id":4432,"t":"וְאַמְרָפֶל֙","p":"ואמרפל","c":14,"v":9},{"id":4433,"t":"מֶ֣לֶךְ","p":"מלך","c":14,"v":9},{"id":4434,"t":"שִׁנְעָ֔ר","p":"שנער","c":14,"v":9},{"id":4435,"t":"וְאַרְי֖וֹךְ","p":"ואריוך","c":14,"v":9},{"id":4436,"t":"מֶ֣לֶךְ","p":"מלך","c":14,"v":9},{"id":4437,"t":"אֶלָּסָ֑ר","p":"אלסר","c":14,"v":9},{"id":4438,"t":"אַרְבָּעָ֥ה","p":"ארבעה","c":14,"v":9},{"id":4439,"t":"מְלָכִ֖ים","p":"מלכים","c":14,"v":9},{"id":4440,"t":"אֶת","p":"את","c":14,"v":9},{"id":4441,"t":"הַחֲמִשָּֽׁה","p":"החמשה","c":14,"v":9},{"id":4442,"t":"וְעֵ֣מֶק","p":"ועמק","c":14,"v":10},{"id":4443,"t":"הַשִּׂדִּ֗ים","p":"השדים","c":14,"v":10},{"id":4444,"t":"בֶּֽאֱרֹ֤ת","p":"בארת","c":14,"v":10},{"id":4445,"t":"בֶּאֱרֹת֙","p":"בארת","c":14,"v":10},{"id":4446,"t":"חֵמָ֔ר","p":"חמר","c":14,"v":10},{"id":4447,"t":"וַיָּנֻ֛סוּ","p":"וינסו","c":14,"v":10},{"id":4448,"t":"מֶֽלֶךְ","p":"מלך","c":14,"v":10},{"id":4449,"t":"סְדֹ֥ם","p":"סדם","c":14,"v":10},{"id":4450,"t":"וַעֲמֹרָ֖ה","p":"ועמרה","c":14,"v":10},{"id":4451,"t":"וַיִּפְּלוּ","p":"ויפלו","c":14,"v":10},{"id":4452,"t":"שָׁ֑מָּה","p":"שמה","c":14,"v":10},{"id":4453,"t":"וְהַנִּשְׁאָרִ֖ים","p":"והנשארים","c":14,"v":10},{"id":4454,"t":"הֶ֥רָה","p":"הרה","c":14,"v":10},{"id":4455,"t":"נָּֽסוּ","p":"נסו","c":14,"v":10},{"id":4456,"t":"וַ֠יִּקְח֠וּ","p":"ויקחו","c":14,"v":11},{"id":4457,"t":"אֶת","p":"את","c":14,"v":11},{"id":4458,"t":"כׇּל","p":"כל","c":14,"v":11},{"id":4459,"t":"רְכֻ֨שׁ","p":"רכש","c":14,"v":11},{"id":4460,"t":"סְדֹ֧ם","p":"סדם","c":14,"v":11},{"id":4461,"t":"וַעֲמֹרָ֛ה","p":"ועמרה","c":14,"v":11},{"id":4462,"t":"וְאֶת","p":"ואת","c":14,"v":11},{"id":4463,"t":"כׇּל","p":"כל","c":14,"v":11},{"id":4464,"t":"אׇכְלָ֖ם","p":"אכלם","c":14,"v":11},{"id":4465,"t":"וַיֵּלֵֽכוּ","p":"וילכו","c":14,"v":11},{"id":4466,"t":"וַיִּקְח֨וּ","p":"ויקחו","c":14,"v":12},{"id":4467,"t":"אֶת","p":"את","c":14,"v":12},{"id":4468,"t":"ל֧וֹט","p":"לוט","c":14,"v":12},{"id":4469,"t":"וְאֶת","p":"ואת","c":14,"v":12},{"id":4470,"t":"רְכֻשׁ֛וֹ","p":"רכשו","c":14,"v":12},{"id":4471,"t":"בֶּן","p":"בן","c":14,"v":12},{"id":4472,"t":"אֲחִ֥י","p":"אחי","c":14,"v":12},{"id":4473,"t":"אַבְרָ֖ם","p":"אברם","c":14,"v":12},{"id":4474,"t":"וַיֵּלֵ֑כוּ","p":"וילכו","c":14,"v":12},{"id":4475,"t":"וְה֥וּא","p":"והוא","c":14,"v":12},{"id":4476,"t":"יֹשֵׁ֖ב","p":"ישב","c":14,"v":12},{"id":4477,"t":"בִּסְדֹֽם","p":"בסדם","c":14,"v":12},{"id":4478,"t":"וַיָּבֹא֙","p":"ויבא","c":14,"v":13},{"id":4479,"t":"הַפָּלִ֔יט","p":"הפליט","c":14,"v":13},{"id":4480,"t":"וַיַּגֵּ֖ד","p":"ויגד","c":14,"v":13},{"id":4481,"t":"לְאַבְרָ֣ם","p":"לאברם","c":14,"v":13},{"id":4482,"t":"הָעִבְרִ֑י","p":"העברי","c":14,"v":13},{"id":4483,"t":"וְהוּא֩","p":"והוא","c":14,"v":13},{"id":4484,"t":"שֹׁכֵ֨ן","p":"שכן","c":14,"v":13},{"id":4485,"t":"בְּאֵֽלֹנֵ֜י","p":"באלני","c":14,"v":13},{"id":4486,"t":"מַמְרֵ֣א","p":"ממרא","c":14,"v":13},{"id":4487,"t":"הָאֱמֹרִ֗י","p":"האמרי","c":14,"v":13},{"id":4488,"t":"אֲחִ֤י","p":"אחי","c":14,"v":13},{"id":4489,"t":"אֶשְׁכֹּל֙","p":"אשכל","c":14,"v":13},{"id":4490,"t":"וַאֲחִ֣י","p":"ואחי","c":14,"v":13},{"id":4491,"t":"עָנֵ֔ר","p":"ענר","c":14,"v":13},{"id":4492,"t":"וְהֵ֖ם","p":"והם","c":14,"v":13},{"id":4493,"t":"בַּעֲלֵ֥י","p":"בעלי","c":14,"v":13},{"id":4494,"t":"בְרִית","p":"ברית","c":14,"v":13},{"id":4495,"t":"אַבְרָֽם","p":"אברם","c":14,"v":13},{"id":4496,"t":"וַיִּשְׁמַ֣ע","p":"וישמע","c":14,"v":14},{"id":4497,"t":"אַבְרָ֔ם","p":"אברם","c":14,"v":14},{"id":4498,"t":"כִּ֥י","p":"כי","c":14,"v":14},{"id":4499,"t":"נִשְׁבָּ֖ה","p":"נשבה","c":14,"v":14},{"id":4500,"t":"אָחִ֑יו","p":"אחיו","c":14,"v":14},{"id":4501,"t":"וַיָּ֨רֶק","p":"וירק","c":14,"v":14},{"id":4502,"t":"אֶת","p":"את","c":14,"v":14},{"id":4503,"t":"חֲנִיכָ֜יו","p":"חניכיו","c":14,"v":14},{"id":4504,"t":"יְלִידֵ֣י","p":"ילידי","c":14,"v":14},{"id":4505,"t":"בֵית֗וֹ","p":"ביתו","c":14,"v":14},{"id":4506,"t":"שְׁמֹנָ֤ה","p":"שמנה","c":14,"v":14},{"id":4507,"t":"עָשָׂר֙","p":"עשר","c":14,"v":14},{"id":4508,"t":"וּשְׁלֹ֣שׁ","p":"ושלש","c":14,"v":14},{"id":4509,"t":"מֵא֔וֹת","p":"מאות","c":14,"v":14},{"id":4510,"t":"וַיִּרְדֹּ֖ף","p":"וירדף","c":14,"v":14},{"id":4511,"t":"עַד","p":"עד","c":14,"v":14},{"id":4512,"t":"דָּֽן","p":"דן","c":14,"v":14},{"id":4513,"t":"וַיֵּחָלֵ֨ק","p":"ויחלק","c":14,"v":15},{"id":4514,"t":"עֲלֵיהֶ֧ם","p":"עליהם","c":14,"v":15},{"id":4515,"t":"׀","p":"לילה","c":14,"v":15},{"id":4516,"t":"לַ֛יְלָה","p":"הוא","c":14,"v":15},{"id":4517,"t":"ה֥וּא","p":"ועבדיו","c":14,"v":15},{"id":4518,"t":"וַעֲבָדָ֖יו","p":"ויכם","c":14,"v":15},{"id":4519,"t":"וַיַּכֵּ֑ם","p":"וירדפם","c":14,"v":15},{"id":4520,"t":"וַֽיִּרְדְּפֵם֙","p":"עד","c":14,"v":15},{"id":4521,"t":"עַד","p":"חובה","c":14,"v":15},{"id":4522,"t":"חוֹבָ֔ה","p":"אשר","c":14,"v":15},{"id":4523,"t":"אֲשֶׁ֥ר","p":"משמאל","c":14,"v":15},{"id":4524,"t":"מִשְּׂמֹ֖אל","p":"לדמשק","c":14,"v":15},{"id":4525,"t":"וַיָּ֕שֶׁב","p":"וישב","c":14,"v":16},{"id":4526,"t":"אֵ֖ת","p":"את","c":14,"v":16},{"id":4527,"t":"כׇּל","p":"כל","c":14,"v":16},{"id":4528,"t":"הָרְכֻ֑שׁ","p":"הרכש","c":14,"v":16},{"id":4529,"t":"וְגַם֩","p":"וגם","c":14,"v":16},{"id":4530,"t":"אֶת","p":"את","c":14,"v":16},{"id":4531,"t":"ל֨וֹט","p":"לוט","c":14,"v":16},{"id":4532,"t":"אָחִ֤יו","p":"אחיו","c":14,"v":16},{"id":4533,"t":"וּרְכֻשׁוֹ֙","p":"ורכשו","c":14,"v":16},{"id":4534,"t":"הֵשִׁ֔יב","p":"השיב","c":14,"v":16},{"id":4535,"t":"וְגַ֥ם","p":"וגם","c":14,"v":16},{"id":4536,"t":"אֶת","p":"את","c":14,"v":16},{"id":4537,"t":"הַנָּשִׁ֖ים","p":"הנשים","c":14,"v":16},{"id":4538,"t":"וְאֶת","p":"ואת","c":14,"v":16},{"id":4539,"t":"הָעָֽם","p":"העם","c":14,"v":16},{"id":4540,"t":"וַיֵּצֵ֣א","p":"ויצא","c":14,"v":17},{"id":4541,"t":"מֶֽלֶךְ","p":"מלך","c":14,"v":17},{"id":4542,"t":"סְדֹם֮","p":"סדם","c":14,"v":17},{"id":4543,"t":"לִקְרָאתוֹ֒","p":"לקראתו","c":14,"v":17},{"id":4544,"t":"אַחֲרֵ֣י","p":"אחרי","c":14,"v":17},{"id":4545,"t":"שׁוּב֗וֹ","p":"שובו","c":14,"v":17},{"id":4546,"t":"מֵֽהַכּוֹת֙","p":"מהכות","c":14,"v":17},{"id":4547,"t":"אֶת","p":"את","c":14,"v":17},{"id":4548,"t":"כְּדׇרְלָעֹ֔מֶר","p":"כדרלעמר","c":14,"v":17},{"id":4549,"t":"וְאֶת","p":"ואת","c":14,"v":17},{"id":4550,"t":"הַמְּלָכִ֖ים","p":"המלכים","c":14,"v":17},{"id":4551,"t":"אֲשֶׁ֣ר","p":"אשר","c":14,"v":17},{"id":4552,"t":"אִתּ֑וֹ","p":"אתו","c":14,"v":17},{"id":4553,"t":"אֶל","p":"אל","c":14,"v":17},{"id":4554,"t":"עֵ֣מֶק","p":"עמק","c":14,"v":17},{"id":4555,"t":"שָׁוֵ֔ה","p":"שוה","c":14,"v":17},{"id":4556,"t":"ה֖וּא","p":"הוא","c":14,"v":17},{"id":4557,"t":"עֵ֥מֶק","p":"עמק","c":14,"v":17},{"id":4558,"t":"הַמֶּֽלֶךְ","p":"המלך","c":14,"v":17},{"id":4559,"t":"וּמַלְכִּי","p":"ומלכי","c":14,"v":18},{"id":4560,"t":"צֶ֙דֶק֙","p":"צדק","c":14,"v":18},{"id":4561,"t":"מֶ֣לֶךְ","p":"מלך","c":14,"v":18},{"id":4562,"t":"שָׁלֵ֔ם","p":"שלם","c":14,"v":18},{"id":4563,"t":"הוֹצִ֖יא","p":"הוציא","c":14,"v":18},{"id":4564,"t":"לֶ֣חֶם","p":"לחם","c":14,"v":18},{"id":4565,"t":"וָיָ֑יִן","p":"ויין","c":14,"v":18},{"id":4566,"t":"וְה֥וּא","p":"והוא","c":14,"v":18},{"id":4567,"t":"כֹהֵ֖ן","p":"כהן","c":14,"v":18},{"id":4568,"t":"לְאֵ֥ל","p":"לאל","c":14,"v":18},{"id":4569,"t":"עֶלְיֽוֹן","p":"עליון","c":14,"v":18},{"id":4570,"t":"וַֽיְבָרְכֵ֖הוּ","p":"ויברכהו","c":14,"v":19},{"id":4571,"t":"וַיֹּאמַ֑ר","p":"ויאמר","c":14,"v":19},{"id":4572,"t":"בָּר֤וּךְ","p":"ברוך","c":14,"v":19},{"id":4573,"t":"אַבְרָם֙","p":"אברם","c":14,"v":19},{"id":4574,"t":"לְאֵ֣ל","p":"לאל","c":14,"v":19},{"id":4575,"t":"עֶלְי֔וֹן","p":"עליון","c":14,"v":19},{"id":4576,"t":"קֹנֵ֖ה","p":"קנה","c":14,"v":19},{"id":4577,"t":"שָׁמַ֥יִם","p":"שמים","c":14,"v":19},{"id":4578,"t":"וָאָֽרֶץ","p":"וארץ","c":14,"v":19},{"id":4579,"t":"וּבָרוּךְ֙","p":"וברוך","c":14,"v":20},{"id":4580,"t":"אֵ֣ל","p":"אל","c":14,"v":20},{"id":4581,"t":"עֶלְי֔וֹן","p":"עליון","c":14,"v":20},{"id":4582,"t":"אֲשֶׁר","p":"אשר","c":14,"v":20},{"id":4583,"t":"מִגֵּ֥ן","p":"מגן","c":14,"v":20},{"id":4584,"t":"צָרֶ֖יךָ","p":"צריך","c":14,"v":20},{"id":4585,"t":"בְּיָדֶ֑ךָ","p":"בידך","c":14,"v":20},{"id":4586,"t":"וַיִּתֶּן","p":"ויתן","c":14,"v":20},{"id":4587,"t":"ל֥וֹ","p":"לו","c":14,"v":20},{"id":4588,"t":"מַעֲשֵׂ֖ר","p":"מעשר","c":14,"v":20},{"id":4589,"t":"מִכֹּֽל","p":"מכל","c":14,"v":20},{"id":4590,"t":"וַיֹּ֥אמֶר","p":"ויאמר","c":14,"v":21},{"id":4591,"t":"מֶֽלֶךְ","p":"מלך","c":14,"v":21},{"id":4592,"t":"סְדֹ֖ם","p":"סדם","c":14,"v":21},{"id":4593,"t":"אֶל","p":"אל","c":14,"v":21},{"id":4594,"t":"אַבְרָ֑ם","p":"אברם","c":14,"v":21},{"id":4595,"t":"תֶּן","p":"תן","c":14,"v":21},{"id":4596,"t":"לִ֣י","p":"לי","c":14,"v":21},{"id":4597,"t":"הַנֶּ֔פֶשׁ","p":"הנפש","c":14,"v":21},{"id":4598,"t":"וְהָרְכֻ֖שׁ","p":"והרכש","c":14,"v":21},{"id":4599,"t":"קַֽח","p":"קח","c":14,"v":21},{"id":4600,"t":"לָֽךְ","p":"לך","c":14,"v":21},{"id":4601,"t":"וַיֹּ֥אמֶר","p":"ויאמר","c":14,"v":22},{"id":4602,"t":"אַבְרָ֖ם","p":"אברם","c":14,"v":22},{"id":4603,"t":"אֶל","p":"אל","c":14,"v":22},{"id":4604,"t":"מֶ֣לֶךְ","p":"מלך","c":14,"v":22},{"id":4605,"t":"סְדֹ֑ם","p":"סדם","c":14,"v":22},{"id":4606,"t":"הֲרִמֹ֨תִי","p":"הרימתי","c":14,"v":22},{"id":4607,"t":"יָדִ֤י","p":"ידי","c":14,"v":22},{"id":4608,"t":"אֶל","p":"אל","c":14,"v":22},{"id":4609,"t":"יְהֹוָה֙","p":"יהוה","c":14,"v":22},{"id":4610,"t":"אֵ֣ל","p":"אל","c":14,"v":22},{"id":4611,"t":"עֶלְי֔וֹן","p":"עליון","c":14,"v":22},{"id":4612,"t":"קֹנֵ֖ה","p":"קנה","c":14,"v":22},{"id":4613,"t":"שָׁמַ֥יִם","p":"שמים","c":14,"v":22},{"id":4614,"t":"וָאָֽרֶץ","p":"וארץ","c":14,"v":22},{"id":4615,"t":"אִם","p":"אם","c":14,"v":23},{"id":4616,"t":"מִחוּט֙","p":"מחוט","c":14,"v":23},{"id":4617,"t":"וְעַ֣ד","p":"ועד","c":14,"v":23},{"id":4618,"t":"שְׂרֽוֹךְ","p":"שרוך","c":14,"v":23},{"id":4619,"t":"נַ֔עַל","p":"נעל","c":14,"v":23},{"id":4620,"t":"וְאִם","p":"ואם","c":14,"v":23},{"id":4621,"t":"אֶקַּ֖ח","p":"אקח","c":14,"v":23},{"id":4622,"t":"מִכׇּל","p":"מכל","c":14,"v":23},{"id":4623,"t":"אֲשֶׁר","p":"אשר","c":14,"v":23},{"id":4624,"t":"לָ֑ךְ","p":"לך","c":14,"v":23},{"id":4625,"t":"וְלֹ֣א","p":"ולא","c":14,"v":23},{"id":4626,"t":"תֹאמַ֔ר","p":"תאמר","c":14,"v":23},{"id":4627,"t":"אֲנִ֖י","p":"אני","c":14,"v":23},{"id":4628,"t":"הֶעֱשַׁ֥רְתִּי","p":"העשרתי","c":14,"v":23},{"id":4629,"t":"אֶת","p":"את","c":14,"v":23},{"id":4630,"t":"אַבְרָֽם","p":"אברם","c":14,"v":23},{"id":4631,"t":"בִּלְעָדַ֗י","p":"בלעדי","c":14,"v":24},{"id":4632,"t":"רַ֚ק","p":"רק","c":14,"v":24},{"id":4633,"t":"אֲשֶׁ֣ר","p":"אשר","c":14,"v":24},{"id":4634,"t":"אָֽכְל֣וּ","p":"אכלו","c":14,"v":24},{"id":4635,"t":"הַנְּעָרִ֔ים","p":"הנערים","c":14,"v":24},{"id":4636,"t":"וְחֵ֙לֶק֙","p":"וחלק","c":14,"v":24},{"id":4637,"t":"הָֽאֲנָשִׁ֔ים","p":"האנשים","c":14,"v":24},{"id":4638,"t":"אֲשֶׁ֥ר","p":"אשר","c":14,"v":24},{"id":4639,"t":"הָלְכ֖וּ","p":"הלכו","c":14,"v":24},{"id":4640,"t":"אִתִּ֑י","p":"אתי","c":14,"v":24},{"id":4641,"t":"עָנֵר֙","p":"ענר","c":14,"v":24},{"id":4642,"t":"אֶשְׁכֹּ֣ל","p":"אשכל","c":14,"v":24},{"id":4643,"t":"וּמַמְרֵ֔א","p":"וממרא","c":14,"v":24},{"id":4644,"t":"הֵ֖ם","p":"הם","c":14,"v":24},{"id":4645,"t":"יִקְח֥וּ","p":"יקחו","c":14,"v":24},{"id":4646,"t":"חֶלְקָֽם","p":"חלקם","c":14,"v":24},{"id":4647,"t":"אַחַ֣ר","p":"אחר","c":15,"v":1},{"id":4648,"t":"׀","p":"הדברים","c":15,"v":1},{"id":4649,"t":"הַדְּבָרִ֣ים","p":"האלה","c":15,"v":1},{"id":4650,"t":"הָאֵ֗לֶּה","p":"היה","c":15,"v":1},{"id":4651,"t":"הָיָ֤ה","p":"דבר","c":15,"v":1},{"id":4652,"t":"דְבַר","p":"יהוה","c":15,"v":1},{"id":4653,"t":"יְהֹוָה֙","p":"אל","c":15,"v":1},{"id":4654,"t":"אֶל","p":"אברם","c":15,"v":1},{"id":4655,"t":"אַבְרָ֔ם","p":"במחזה","c":15,"v":1},{"id":4656,"t":"בַּֽמַּחֲזֶ֖ה","p":"לאמר","c":15,"v":1},{"id":4657,"t":"לֵאמֹ֑ר","p":"אל","c":15,"v":1},{"id":4658,"t":"אַל","p":"תירא","c":15,"v":1},{"id":4659,"t":"תִּירָ֣א","p":"אברם","c":15,"v":1},{"id":4660,"t":"אַבְרָ֗ם","p":"אנכי","c":15,"v":1},{"id":4661,"t":"אָנֹכִי֙","p":"מגן","c":15,"v":1},{"id":4662,"t":"מָגֵ֣ן","p":"לך","c":15,"v":1},{"id":4663,"t":"לָ֔ךְ","p":"שכרך","c":15,"v":1},{"id":4664,"t":"שְׂכָרְךָ֖","p":"הרבה","c":15,"v":1},{"id":4665,"t":"הַרְבֵּ֥ה","p":"מאד","c":15,"v":1},{"id":4666,"t":"וַיֹּ֣אמֶר","p":"ויאמר","c":15,"v":2},{"id":4667,"t":"אַבְרָ֗ם","p":"אברם","c":15,"v":2},{"id":4668,"t":"אֲדֹנָ֤י","p":"אדני","c":15,"v":2},{"id":4669,"t":"יֱהֹוִה֙","p":"יהוה","c":15,"v":2},{"id":4670,"t":"מַה","p":"מה","c":15,"v":2},{"id":4671,"t":"תִּתֶּן","p":"תתן","c":15,"v":2},{"id":4672,"t":"לִ֔י","p":"לי","c":15,"v":2},{"id":4673,"t":"וְאָנֹכִ֖י","p":"ואנכי","c":15,"v":2},{"id":4674,"t":"הוֹלֵ֣ךְ","p":"הולך","c":15,"v":2},{"id":4675,"t":"עֲרִירִ֑י","p":"ערירי","c":15,"v":2},{"id":4676,"t":"וּבֶן","p":"ובן","c":15,"v":2},{"id":4677,"t":"מֶ֣שֶׁק","p":"משק","c":15,"v":2},{"id":4678,"t":"בֵּיתִ֔י","p":"ביתי","c":15,"v":2},{"id":4679,"t":"ה֖וּא","p":"הוא","c":15,"v":2},{"id":4680,"t":"דַּמֶּ֥שֶׂק","p":"דמשק","c":15,"v":2},{"id":4681,"t":"אֱלִיעֶֽזֶר","p":"אליעזר","c":15,"v":2},{"id":4682,"t":"וַיֹּ֣אמֶר","p":"ויאמר","c":15,"v":3},{"id":4683,"t":"אַבְרָ֔ם","p":"אברם","c":15,"v":3},{"id":4684,"t":"הֵ֣ן","p":"הן","c":15,"v":3},{"id":4685,"t":"לִ֔י","p":"לי","c":15,"v":3},{"id":4686,"t":"לֹ֥א","p":"לא","c":15,"v":3},{"id":4687,"t":"נָתַ֖תָּה","p":"נתתה","c":15,"v":3},{"id":4688,"t":"זָ֑רַע","p":"זרע","c":15,"v":3},{"id":4689,"t":"וְהִנֵּ֥ה","p":"והנה","c":15,"v":3},{"id":4690,"t":"בֶן","p":"בן","c":15,"v":3},{"id":4691,"t":"בֵּיתִ֖י","p":"ביתי","c":15,"v":3},{"id":4692,"t":"יוֹרֵ֥שׁ","p":"יורש","c":15,"v":3},{"id":4693,"t":"אֹתִֽי","p":"אתי","c":15,"v":3},{"id":4694,"t":"וְהִנֵּ֨ה","p":"והנה","c":15,"v":4},{"id":4695,"t":"דְבַר","p":"דבר","c":15,"v":4},{"id":4696,"t":"יְהֹוָ֤ה","p":"יהוה","c":15,"v":4},{"id":4697,"t":"אֵלָיו֙","p":"אליו","c":15,"v":4},{"id":4698,"t":"לֵאמֹ֔ר","p":"לאמר","c":15,"v":4},{"id":4699,"t":"לֹ֥א","p":"לא","c":15,"v":4},{"id":4700,"t":"יִֽירָשְׁךָ֖","p":"יירשך","c":15,"v":4},{"id":4701,"t":"זֶ֑ה","p":"זה","c":15,"v":4},{"id":4702,"t":"כִּי","p":"כי","c":15,"v":4},{"id":4703,"t":"אִם֙","p":"אם","c":15,"v":4},{"id":4704,"t":"אֲשֶׁ֣ר","p":"אשר","c":15,"v":4},{"id":4705,"t":"יֵצֵ֣א","p":"יצא","c":15,"v":4},{"id":4706,"t":"מִמֵּעֶ֔יךָ","p":"ממעיך","c":15,"v":4},{"id":4707,"t":"ה֖וּא","p":"הוא","c":15,"v":4},{"id":4708,"t":"יִֽירָשֶֽׁךָ","p":"יירשך","c":15,"v":4},{"id":4709,"t":"וַיּוֹצֵ֨א","p":"ויוצא","c":15,"v":5},{"id":4710,"t":"אֹת֜וֹ","p":"אתו","c":15,"v":5},{"id":4711,"t":"הַח֗וּצָה","p":"החוצה","c":15,"v":5},{"id":4712,"t":"וַיֹּ֙אמֶר֙","p":"ויאמר","c":15,"v":5},{"id":4713,"t":"הַבֶּט","p":"הבט","c":15,"v":5},{"id":4714,"t":"נָ֣א","p":"נא","c":15,"v":5},{"id":4715,"t":"הַשָּׁמַ֗יְמָה","p":"השמימה","c":15,"v":5},{"id":4716,"t":"וּסְפֹר֙","p":"וספר","c":15,"v":5},{"id":4717,"t":"הַכּ֣וֹכָבִ֔ים","p":"הכוכבים","c":15,"v":5},{"id":4718,"t":"אִם","p":"אם","c":15,"v":5},{"id":4719,"t":"תּוּכַ֖ל","p":"תוכל","c":15,"v":5},{"id":4720,"t":"לִסְפֹּ֣ר","p":"לספר","c":15,"v":5},{"id":4721,"t":"אֹתָ֑ם","p":"אתם","c":15,"v":5},{"id":4722,"t":"וַיֹּ֣אמֶר","p":"ויאמר","c":15,"v":5},{"id":4723,"t":"ל֔וֹ","p":"לו","c":15,"v":5},{"id":4724,"t":"כֹּ֥ה","p":"כה","c":15,"v":5},{"id":4725,"t":"יִהְיֶ֖ה","p":"יהיה","c":15,"v":5},{"id":4726,"t":"זַרְעֶֽךָ","p":"זרעך","c":15,"v":5},{"id":4727,"t":"וְהֶאֱמִ֖ן","p":"והאמן","c":15,"v":6},{"id":4728,"t":"בַּֽיהֹוָ֑ה","p":"ביהוה","c":15,"v":6},{"id":4729,"t":"וַיַּחְשְׁבֶ֥הָ","p":"ויחשבה","c":15,"v":6},{"id":4730,"t":"לּ֖וֹ","p":"לו","c":15,"v":6},{"id":4731,"t":"צְדָקָֽה","p":"צדקה","c":15,"v":6},{"id":4732,"t":"וַיֹּ֖אמֶר","p":"ויאמר","c":15,"v":7},{"id":4733,"t":"אֵלָ֑יו","p":"אליו","c":15,"v":7},{"id":4734,"t":"אֲנִ֣י","p":"אני","c":15,"v":7},{"id":4735,"t":"יְהֹוָ֗ה","p":"יהוה","c":15,"v":7},{"id":4736,"t":"אֲשֶׁ֤ר","p":"אשר","c":15,"v":7},{"id":4737,"t":"הוֹצֵאתִ֙יךָ֙","p":"הוצאתיך","c":15,"v":7},{"id":4738,"t":"מֵא֣וּר","p":"מאור","c":15,"v":7},{"id":4739,"t":"כַּשְׂדִּ֔ים","p":"כשדים","c":15,"v":7},{"id":4740,"t":"לָ֧תֶת","p":"לתת","c":15,"v":7},{"id":4741,"t":"לְךָ֛","p":"לך","c":15,"v":7},{"id":4742,"t":"אֶת","p":"את","c":15,"v":7},{"id":4743,"t":"הָאָ֥רֶץ","p":"הארץ","c":15,"v":7},{"id":4744,"t":"הַזֹּ֖את","p":"הזאת","c":15,"v":7},{"id":4745,"t":"לְרִשְׁתָּֽהּ","p":"לרשתה","c":15,"v":7},{"id":4746,"t":"וַיֹּאמַ֑ר","p":"ויאמר","c":15,"v":8},{"id":4747,"t":"אֲדֹנָ֣י","p":"אדני","c":15,"v":8},{"id":4748,"t":"יֱהֹוִ֔ה","p":"יהוה","c":15,"v":8},{"id":4749,"t":"בַּמָּ֥ה","p":"במה","c":15,"v":8},{"id":4750,"t":"אֵדַ֖ע","p":"אדע","c":15,"v":8},{"id":4751,"t":"כִּ֥י","p":"כי","c":15,"v":8},{"id":4752,"t":"אִֽירָשֶֽׁנָּה","p":"אירשנה","c":15,"v":8},{"id":4753,"t":"וַיֹּ֣אמֶר","p":"ויאמר","c":15,"v":9},{"id":4754,"t":"אֵלָ֗יו","p":"אליו","c":15,"v":9},{"id":4755,"t":"קְחָ֥ה","p":"קחה","c":15,"v":9},{"id":4756,"t":"לִי֙","p":"לי","c":15,"v":9},{"id":4757,"t":"עֶגְלָ֣ה","p":"עגלה","c":15,"v":9},{"id":4758,"t":"מְשֻׁלֶּ֔שֶׁת","p":"משלשת","c":15,"v":9},{"id":4759,"t":"וְעֵ֥ז","p":"ועז","c":15,"v":9},{"id":4760,"t":"מְשֻׁלֶּ֖שֶׁת","p":"משלשת","c":15,"v":9},{"id":4761,"t":"וְאַ֣יִל","p":"ואיל","c":15,"v":9},{"id":4762,"t":"מְשֻׁלָּ֑שׁ","p":"משלש","c":15,"v":9},{"id":4763,"t":"וְתֹ֖ר","p":"ותר","c":15,"v":9},{"id":4764,"t":"וְגוֹזָֽל","p":"וגוזל","c":15,"v":9},{"id":4765,"t":"וַיִּֽקַּֽח","p":"ויקח","c":15,"v":10},{"id":4766,"t":"ל֣וֹ","p":"לו","c":15,"v":10},{"id":4767,"t":"אֶת","p":"את","c":15,"v":10},{"id":4768,"t":"כׇּל","p":"כל","c":15,"v":10},{"id":4769,"t":"אֵ֗לֶּה","p":"אלה","c":15,"v":10},{"id":4770,"t":"וַיְבַתֵּ֤ר","p":"ויבתר","c":15,"v":10},{"id":4771,"t":"אֹתָם֙","p":"אתם","c":15,"v":10},{"id":4772,"t":"בַּתָּ֔וֶךְ","p":"בתוך","c":15,"v":10},{"id":4773,"t":"וַיִּתֵּ֥ן","p":"ויתן","c":15,"v":10},{"id":4774,"t":"אִישׁ","p":"איש","c":15,"v":10},{"id":4775,"t":"בִּתְר֖וֹ","p":"בתרו","c":15,"v":10},{"id":4776,"t":"לִקְרַ֣את","p":"לקראת","c":15,"v":10},{"id":4777,"t":"רֵעֵ֑הוּ","p":"רעהו","c":15,"v":10},{"id":4778,"t":"וְאֶת","p":"ואת","c":15,"v":10},{"id":4779,"t":"הַצִּפֹּ֖ר","p":"הצפר","c":15,"v":10},{"id":4780,"t":"לֹ֥א","p":"לא","c":15,"v":10},{"id":4781,"t":"בָתָֽר","p":"בתר","c":15,"v":10},{"id":4782,"t":"וַיֵּ֥רֶד","p":"וירד","c":15,"v":11},{"id":4783,"t":"הָעַ֖יִט","p":"העיט","c":15,"v":11},{"id":4784,"t":"עַל","p":"על","c":15,"v":11},{"id":4785,"t":"הַפְּגָרִ֑ים","p":"הפגרים","c":15,"v":11},{"id":4786,"t":"וַיַּשֵּׁ֥ב","p":"וישב","c":15,"v":11},{"id":4787,"t":"אֹתָ֖ם","p":"אתם","c":15,"v":11},{"id":4788,"t":"אַבְרָֽם","p":"אברם","c":15,"v":11},{"id":4789,"t":"וַיְהִ֤י","p":"ויהי","c":15,"v":12},{"id":4790,"t":"הַשֶּׁ֙מֶשׁ֙","p":"השמש","c":15,"v":12},{"id":4791,"t":"לָב֔וֹא","p":"לבוא","c":15,"v":12},{"id":4792,"t":"וְתַרְדֵּמָ֖ה","p":"ותרדמה","c":15,"v":12},{"id":4793,"t":"נָפְלָ֣ה","p":"נפלה","c":15,"v":12},{"id":4794,"t":"עַל","p":"על","c":15,"v":12},{"id":4795,"t":"אַבְרָ֑ם","p":"אברם","c":15,"v":12},{"id":4796,"t":"וְהִנֵּ֥ה","p":"והנה","c":15,"v":12},{"id":4797,"t":"אֵימָ֛ה","p":"אימה","c":15,"v":12},{"id":4798,"t":"חֲשֵׁכָ֥ה","p":"חשכה","c":15,"v":12},{"id":4799,"t":"גְדֹלָ֖ה","p":"גדלה","c":15,"v":12},{"id":4800,"t":"נֹפֶ֥לֶת","p":"נפלת","c":15,"v":12},{"id":4801,"t":"עָלָֽיו","p":"עליו","c":15,"v":12},{"id":4802,"t":"וַיֹּ֣אמֶר","p":"ויאמר","c":15,"v":13},{"id":4803,"t":"לְאַבְרָ֗ם","p":"לאברם","c":15,"v":13},{"id":4804,"t":"יָדֹ֨עַ","p":"ידע","c":15,"v":13},{"id":4805,"t":"תֵּדַ֜ע","p":"תדע","c":15,"v":13},{"id":4806,"t":"כִּי","p":"כי","c":15,"v":13},{"id":4807,"t":"גֵ֣ר","p":"גר","c":15,"v":13},{"id":4808,"t":"׀","p":"יהיה","c":15,"v":13},{"id":4809,"t":"יִהְיֶ֣ה","p":"זרעך","c":15,"v":13},{"id":4810,"t":"זַרְעֲךָ֗","p":"בארץ","c":15,"v":13},{"id":4811,"t":"בְּאֶ֙רֶץ֙","p":"לא","c":15,"v":13},{"id":4812,"t":"לֹ֣א","p":"להם","c":15,"v":13},{"id":4813,"t":"לָהֶ֔ם","p":"ועבדום","c":15,"v":13},{"id":4814,"t":"וַעֲבָד֖וּם","p":"וענו","c":15,"v":13},{"id":4815,"t":"וְעִנּ֣וּ","p":"אתם","c":15,"v":13},{"id":4816,"t":"אֹתָ֑ם","p":"ארבע","c":15,"v":13},{"id":4817,"t":"אַרְבַּ֥ע","p":"מאות","c":15,"v":13},{"id":4818,"t":"מֵא֖וֹת","p":"שנה","c":15,"v":13},{"id":4819,"t":"וְגַ֧ם","p":"וגם","c":15,"v":14},{"id":4820,"t":"אֶת","p":"את","c":15,"v":14},{"id":4821,"t":"הַגּ֛וֹי","p":"הגוי","c":15,"v":14},{"id":4822,"t":"אֲשֶׁ֥ר","p":"אשר","c":15,"v":14},{"id":4823,"t":"יַעֲבֹ֖דוּ","p":"יעבדו","c":15,"v":14},{"id":4824,"t":"דָּ֣ן","p":"דן","c":15,"v":14},{"id":4825,"t":"אָנֹ֑כִי","p":"אנכי","c":15,"v":14},{"id":4826,"t":"וְאַחֲרֵי","p":"ואחרי","c":15,"v":14},{"id":4827,"t":"כֵ֥ן","p":"כן","c":15,"v":14},{"id":4828,"t":"יֵצְא֖וּ","p":"יצאו","c":15,"v":14},{"id":4829,"t":"בִּרְכֻ֥שׁ","p":"ברכש","c":15,"v":14},{"id":4830,"t":"גָּדֽוֹל","p":"גדול","c":15,"v":14},{"id":4831,"t":"וְאַתָּ֛ה","p":"ואתה","c":15,"v":15},{"id":4832,"t":"תָּב֥וֹא","p":"תבוא","c":15,"v":15},{"id":4833,"t":"אֶל","p":"אל","c":15,"v":15},{"id":4834,"t":"אֲבֹתֶ֖יךָ","p":"אבתיך","c":15,"v":15},{"id":4835,"t":"בְּשָׁל֑וֹם","p":"בשלום","c":15,"v":15},{"id":4836,"t":"תִּקָּבֵ֖ר","p":"תקבר","c":15,"v":15},{"id":4837,"t":"בְּשֵׂיבָ֥ה","p":"בשיבה","c":15,"v":15},{"id":4838,"t":"טוֹבָֽה","p":"טובה","c":15,"v":15},{"id":4839,"t":"וְד֥וֹר","p":"ודור","c":15,"v":16},{"id":4840,"t":"רְבִיעִ֖י","p":"רביעי","c":15,"v":16},{"id":4841,"t":"יָשׁ֣וּבוּ","p":"ישובו","c":15,"v":16},{"id":4842,"t":"הֵ֑נָּה","p":"הנה","c":15,"v":16},{"id":4843,"t":"כִּ֧י","p":"כי","c":15,"v":16},{"id":4844,"t":"לֹא","p":"לא","c":15,"v":16},{"id":4845,"t":"שָׁלֵ֛ם","p":"שלם","c":15,"v":16},{"id":4846,"t":"עֲוֺ֥ן","p":"עון","c":15,"v":16},{"id":4847,"t":"הָאֱמֹרִ֖י","p":"האמרי","c":15,"v":16},{"id":4848,"t":"עַד","p":"עד","c":15,"v":16},{"id":4849,"t":"הֵֽנָּה","p":"הנה","c":15,"v":16},{"id":4850,"t":"וַיְהִ֤י","p":"ויהי","c":15,"v":17},{"id":4851,"t":"הַשֶּׁ֙מֶשׁ֙","p":"השמש","c":15,"v":17},{"id":4852,"t":"בָּ֔אָה","p":"באה","c":15,"v":17},{"id":4853,"t":"וַעֲלָטָ֖ה","p":"ועלטה","c":15,"v":17},{"id":4854,"t":"הָיָ֑ה","p":"היה","c":15,"v":17},{"id":4855,"t":"וְהִנֵּ֨ה","p":"והנה","c":15,"v":17},{"id":4856,"t":"תַנּ֤וּר","p":"תנור","c":15,"v":17},{"id":4857,"t":"עָשָׁן֙","p":"עשן","c":15,"v":17},{"id":4858,"t":"וְלַפִּ֣יד","p":"ולפיד","c":15,"v":17},{"id":4859,"t":"אֵ֔שׁ","p":"אש","c":15,"v":17},{"id":4860,"t":"אֲשֶׁ֣ר","p":"אשר","c":15,"v":17},{"id":4861,"t":"עָבַ֔ר","p":"עבר","c":15,"v":17},{"id":4862,"t":"בֵּ֖ין","p":"בין","c":15,"v":17},{"id":4863,"t":"הַגְּזָרִ֥ים","p":"הגזרים","c":15,"v":17},{"id":4864,"t":"הָאֵֽלֶּה","p":"האלה","c":15,"v":17},{"id":4865,"t":"בַּיּ֣וֹם","p":"ביום","c":15,"v":18},{"id":4866,"t":"הַה֗וּא","p":"ההוא","c":15,"v":18},{"id":4867,"t":"כָּרַ֧ת","p":"כרת","c":15,"v":18},{"id":4868,"t":"יְהֹוָ֛ה","p":"יהוה","c":15,"v":18},{"id":4869,"t":"אֶת","p":"את","c":15,"v":18},{"id":4870,"t":"אַבְרָ֖ם","p":"אברם","c":15,"v":18},{"id":4871,"t":"בְּרִ֣ית","p":"ברית","c":15,"v":18},{"id":4872,"t":"לֵאמֹ֑ר","p":"לאמר","c":15,"v":18},{"id":4873,"t":"לְזַרְעֲךָ֗","p":"לזרעך","c":15,"v":18},{"id":4874,"t":"נָתַ֙תִּי֙","p":"נתתי","c":15,"v":18},{"id":4875,"t":"אֶת","p":"את","c":15,"v":18},{"id":4876,"t":"הָאָ֣רֶץ","p":"הארץ","c":15,"v":18},{"id":4877,"t":"הַזֹּ֔את","p":"הזאת","c":15,"v":18},{"id":4878,"t":"מִנְּהַ֣ר","p":"מנהר","c":15,"v":18},{"id":4879,"t":"מִצְרַ֔יִם","p":"מצרים","c":15,"v":18},{"id":4880,"t":"עַד","p":"עד","c":15,"v":18},{"id":4881,"t":"הַנָּהָ֥ר","p":"הנהר","c":15,"v":18},{"id":4882,"t":"הַגָּדֹ֖ל","p":"הגדל","c":15,"v":18},{"id":4883,"t":"נְהַר","p":"נהר","c":15,"v":18},{"id":4884,"t":"פְּרָֽת","p":"פרת","c":15,"v":18},{"id":4885,"t":"אֶת","p":"את","c":15,"v":19},{"id":4886,"t":"הַקֵּינִי֙","p":"הקיני","c":15,"v":19},{"id":4887,"t":"וְאֶת","p":"ואת","c":15,"v":19},{"id":4888,"t":"הַקְּנִזִּ֔י","p":"הקנזי","c":15,"v":19},{"id":4889,"t":"וְאֵ֖ת","p":"ואת","c":15,"v":19},{"id":4890,"t":"הַקַּדְמֹנִֽי","p":"הקדמני","c":15,"v":19},{"id":4891,"t":"וְאֶת","p":"ואת","c":15,"v":20},{"id":4892,"t":"הַחִתִּ֥י","p":"החתי","c":15,"v":20},{"id":4893,"t":"וְאֶת","p":"ואת","c":15,"v":20},{"id":4894,"t":"הַפְּרִזִּ֖י","p":"הפרזי","c":15,"v":20},{"id":4895,"t":"וְאֶת","p":"ואת","c":15,"v":20},{"id":4896,"t":"הָרְפָאִֽים","p":"הרפאים","c":15,"v":20},{"id":4897,"t":"וְאֶת","p":"ואת","c":15,"v":21},{"id":4898,"t":"הָֽאֱמֹרִי֙","p":"האמרי","c":15,"v":21},{"id":4899,"t":"וְאֶת","p":"ואת","c":15,"v":21},{"id":4900,"t":"הַֽכְּנַעֲנִ֔י","p":"הכנעני","c":15,"v":21},{"id":4901,"t":"וְאֶת","p":"ואת","c":15,"v":21},{"id":4902,"t":"הַגִּרְגָּשִׁ֖י","p":"הגרגשי","c":15,"v":21},{"id":4903,"t":"וְאֶת","p":"ואת","c":15,"v":21},{"id":4904,"t":"הַיְבוּסִֽי","p":"היבוסי","c":15,"v":21},{"id":4905,"t":"וְשָׂרַי֙","p":"ושרי","c":16,"v":1},{"id":4906,"t":"אֵ֣שֶׁת","p":"אשת","c":16,"v":1},{"id":4907,"t":"אַבְרָ֔ם","p":"אברם","c":16,"v":1},{"id":4908,"t":"לֹ֥א","p":"לא","c":16,"v":1},{"id":4909,"t":"יָלְדָ֖ה","p":"ילדה","c":16,"v":1},{"id":4910,"t":"ל֑וֹ","p":"לו","c":16,"v":1},{"id":4911,"t":"וְלָ֛הּ","p":"ולה","c":16,"v":1},{"id":4912,"t":"שִׁפְחָ֥ה","p":"שפחה","c":16,"v":1},{"id":4913,"t":"מִצְרִ֖ית","p":"מצרית","c":16,"v":1},{"id":4914,"t":"וּשְׁמָ֥הּ","p":"ושמה","c":16,"v":1},{"id":4915,"t":"הָגָֽר","p":"הגר","c":16,"v":1},{"id":4916,"t":"וַתֹּ֨אמֶר","p":"ותאמר","c":16,"v":2},{"id":4917,"t":"שָׂרַ֜י","p":"שרי","c":16,"v":2},{"id":4918,"t":"אֶל","p":"אל","c":16,"v":2},{"id":4919,"t":"אַבְרָ֗ם","p":"אברם","c":16,"v":2},{"id":4920,"t":"הִנֵּה","p":"הנה","c":16,"v":2},{"id":4921,"t":"נָ֞א","p":"נא","c":16,"v":2},{"id":4922,"t":"עֲצָרַ֤נִי","p":"עצרני","c":16,"v":2},{"id":4923,"t":"יְהֹוָה֙","p":"יהוה","c":16,"v":2},{"id":4924,"t":"מִלֶּ֔דֶת","p":"מלדת","c":16,"v":2},{"id":4925,"t":"בֹּא","p":"בא","c":16,"v":2},{"id":4926,"t":"נָא֙","p":"נא","c":16,"v":2},{"id":4927,"t":"אֶל","p":"אל","c":16,"v":2},{"id":4928,"t":"שִׁפְחָתִ֔י","p":"שפחתי","c":16,"v":2},{"id":4929,"t":"אוּלַ֥י","p":"אולי","c":16,"v":2},{"id":4930,"t":"אִבָּנֶ֖ה","p":"אבנה","c":16,"v":2},{"id":4931,"t":"מִמֶּ֑נָּה","p":"ממנה","c":16,"v":2},{"id":4932,"t":"וַיִּשְׁמַ֥ע","p":"וישמע","c":16,"v":2},{"id":4933,"t":"אַבְרָ֖ם","p":"אברם","c":16,"v":2},{"id":4934,"t":"לְק֥וֹל","p":"לקול","c":16,"v":2},{"id":4935,"t":"שָׂרָֽי","p":"שרי","c":16,"v":2},{"id":4936,"t":"וַתִּקַּ֞ח","p":"ותקח","c":16,"v":3},{"id":4937,"t":"שָׂרַ֣י","p":"שרי","c":16,"v":3},{"id":4938,"t":"אֵֽשֶׁת","p":"אשת","c":16,"v":3},{"id":4939,"t":"אַבְרָ֗ם","p":"אברם","c":16,"v":3},{"id":4940,"t":"אֶת","p":"את","c":16,"v":3},{"id":4941,"t":"הָגָ֤ר","p":"הגר","c":16,"v":3},{"id":4942,"t":"הַמִּצְרִית֙","p":"המצרית","c":16,"v":3},{"id":4943,"t":"שִׁפְחָתָ֔הּ","p":"שפחתה","c":16,"v":3},{"id":4944,"t":"מִקֵּץ֙","p":"מקץ","c":16,"v":3},{"id":4945,"t":"עֶ֣שֶׂר","p":"עשר","c":16,"v":3},{"id":4946,"t":"שָׁנִ֔ים","p":"שנים","c":16,"v":3},{"id":4947,"t":"לְשֶׁ֥בֶת","p":"לשבת","c":16,"v":3},{"id":4948,"t":"אַבְרָ֖ם","p":"אברם","c":16,"v":3},{"id":4949,"t":"בְּאֶ֣רֶץ","p":"בארץ","c":16,"v":3},{"id":4950,"t":"כְּנָ֑עַן","p":"כנען","c":16,"v":3},{"id":4951,"t":"וַתִּתֵּ֥ן","p":"ותתן","c":16,"v":3},{"id":4952,"t":"אֹתָ֛הּ","p":"אתה","c":16,"v":3},{"id":4953,"t":"לְאַבְרָ֥ם","p":"לאברם","c":16,"v":3},{"id":4954,"t":"אִישָׁ֖הּ","p":"אישה","c":16,"v":3},{"id":4955,"t":"ל֥וֹ","p":"לו","c":16,"v":3},{"id":4956,"t":"לְאִשָּֽׁה","p":"לאשה","c":16,"v":3},{"id":4957,"t":"וַיָּבֹ֥א","p":"ויבא","c":16,"v":4},{"id":4958,"t":"אֶל","p":"אל","c":16,"v":4},{"id":4959,"t":"הָגָ֖ר","p":"הגר","c":16,"v":4},{"id":4960,"t":"וַתַּ֑הַר","p":"ותהר","c":16,"v":4},{"id":4961,"t":"וַתֵּ֙רֶא֙","p":"ותרא","c":16,"v":4},{"id":4962,"t":"כִּ֣י","p":"כי","c":16,"v":4},{"id":4963,"t":"הָרָ֔תָה","p":"הרתה","c":16,"v":4},{"id":4964,"t":"וַתֵּקַ֥ל","p":"ותקל","c":16,"v":4},{"id":4965,"t":"גְּבִרְתָּ֖הּ","p":"גברתה","c":16,"v":4},{"id":4966,"t":"בְּעֵינֶֽיהָ","p":"בעיניה","c":16,"v":4},{"id":4967,"t":"וַתֹּ֨אמֶר","p":"ותאמר","c":16,"v":5},{"id":4968,"t":"שָׂרַ֣י","p":"שרי","c":16,"v":5},{"id":4969,"t":"אֶל","p":"אל","c":16,"v":5},{"id":4970,"t":"אַבְרָם֮","p":"אברם","c":16,"v":5},{"id":4971,"t":"חֲמָסִ֣י","p":"חמסי","c":16,"v":5},{"id":4972,"t":"עָלֶ֒יךָ֒","p":"עליך","c":16,"v":5},{"id":4973,"t":"אָנֹכִ֗י","p":"אנכי","c":16,"v":5},{"id":4974,"t":"נָתַ֤תִּי","p":"נתתי","c":16,"v":5},{"id":4975,"t":"שִׁפְחָתִי֙","p":"שפחתי","c":16,"v":5},{"id":4976,"t":"בְּחֵיקֶ֔ךָ","p":"בחיקך","c":16,"v":5},{"id":4977,"t":"וַתֵּ֙רֶא֙","p":"ותרא","c":16,"v":5},{"id":4978,"t":"כִּ֣י","p":"כי","c":16,"v":5},{"id":4979,"t":"הָרָ֔תָה","p":"הרתה","c":16,"v":5},{"id":4980,"t":"וָאֵקַ֖ל","p":"ואקל","c":16,"v":5},{"id":4981,"t":"בְּעֵינֶ֑יהָ","p":"בעיניה","c":16,"v":5},{"id":4982,"t":"יִשְׁפֹּ֥ט","p":"ישפט","c":16,"v":5},{"id":4983,"t":"יְהֹוָ֖ה","p":"יהוה","c":16,"v":5},{"id":4984,"t":"בֵּינִ֥י","p":"ביני","c":16,"v":5},{"id":4985,"t":"וּבֵינֶֽיׄךָ","p":"וביניך","c":16,"v":5},{"id":4986,"t":"וַיֹּ֨אמֶר","p":"ויאמר","c":16,"v":6},{"id":4987,"t":"אַבְרָ֜ם","p":"אברם","c":16,"v":6},{"id":4988,"t":"אֶל","p":"אל","c":16,"v":6},{"id":4989,"t":"שָׂרַ֗י","p":"שרי","c":16,"v":6},{"id":4990,"t":"הִנֵּ֤ה","p":"הנה","c":16,"v":6},{"id":4991,"t":"שִׁפְחָתֵךְ֙","p":"שפחתך","c":16,"v":6},{"id":4992,"t":"בְּיָדֵ֔ךְ","p":"בידך","c":16,"v":6},{"id":4993,"t":"עֲשִׂי","p":"עשי","c":16,"v":6},{"id":4994,"t":"לָ֖הּ","p":"לה","c":16,"v":6},{"id":4995,"t":"הַטּ֣וֹב","p":"הטוב","c":16,"v":6},{"id":4996,"t":"בְּעֵינָ֑יִךְ","p":"בעיניך","c":16,"v":6},{"id":4997,"t":"וַתְּעַנֶּ֣הָ","p":"ותענה","c":16,"v":6},{"id":4998,"t":"שָׂרַ֔י","p":"שרי","c":16,"v":6},{"id":4999,"t":"וַתִּבְרַ֖ח","p":"ותברח","c":16,"v":6},{"id":5000,"t":"מִפָּנֶֽיהָ","p":"מפניה","c":16,"v":6},{"id":5001,"t":"וַֽיִּמְצָאָ֞הּ","p":"וימצאה","c":16,"v":7},{"id":5002,"t":"מַלְאַ֧ךְ","p":"מלאך","c":16,"v":7},{"id":5003,"t":"יְהֹוָ֛ה","p":"יהוה","c":16,"v":7},{"id":5004,"t":"עַל","p":"על","c":16,"v":7},{"id":5005,"t":"עֵ֥ין","p":"עין","c":16,"v":7},{"id":5006,"t":"הַמַּ֖יִם","p":"המים","c":16,"v":7},{"id":5007,"t":"בַּמִּדְבָּ֑ר","p":"במדבר","c":16,"v":7},{"id":5008,"t":"עַל","p":"על","c":16,"v":7},{"id":5009,"t":"הָעַ֖יִן","p":"העין","c":16,"v":7},{"id":5010,"t":"בְּדֶ֥רֶךְ","p":"בדרך","c":16,"v":7},{"id":5011,"t":"שֽׁוּר","p":"שור","c":16,"v":7},{"id":5012,"t":"וַיֹּאמַ֗ר","p":"ויאמר","c":16,"v":8},{"id":5013,"t":"הָגָ֞ר","p":"הגר","c":16,"v":8},{"id":5014,"t":"שִׁפְחַ֥ת","p":"שפחת","c":16,"v":8},{"id":5015,"t":"שָׂרַ֛י","p":"שרי","c":16,"v":8},{"id":5016,"t":"אֵֽי","p":"אי","c":16,"v":8},{"id":5017,"t":"מִזֶּ֥ה","p":"מזה","c":16,"v":8},{"id":5018,"t":"בָ֖את","p":"באת","c":16,"v":8},{"id":5019,"t":"וְאָ֣נָה","p":"ואנה","c":16,"v":8},{"id":5020,"t":"תֵלֵ֑כִי","p":"תלכי","c":16,"v":8},{"id":5021,"t":"וַתֹּ֕אמֶר","p":"ותאמר","c":16,"v":8},{"id":5022,"t":"מִפְּנֵי֙","p":"מפני","c":16,"v":8},{"id":5023,"t":"שָׂרַ֣י","p":"שרי","c":16,"v":8},{"id":5024,"t":"גְּבִרְתִּ֔י","p":"גברתי","c":16,"v":8},{"id":5025,"t":"אָנֹכִ֖י","p":"אנכי","c":16,"v":8},{"id":5026,"t":"בֹּרַֽחַת","p":"ברחת","c":16,"v":8},{"id":5027,"t":"וַיֹּ֤אמֶר","p":"ויאמר","c":16,"v":9},{"id":5028,"t":"לָהּ֙","p":"לה","c":16,"v":9},{"id":5029,"t":"מַלְאַ֣ךְ","p":"מלאך","c":16,"v":9},{"id":5030,"t":"יְהֹוָ֔ה","p":"יהוה","c":16,"v":9},{"id":5031,"t":"שׁ֖וּבִי","p":"שובי","c":16,"v":9},{"id":5032,"t":"אֶל","p":"אל","c":16,"v":9},{"id":5033,"t":"גְּבִרְתֵּ֑ךְ","p":"גברתך","c":16,"v":9},{"id":5034,"t":"וְהִתְעַנִּ֖י","p":"והתעני","c":16,"v":9},{"id":5035,"t":"תַּ֥חַת","p":"תחת","c":16,"v":9},{"id":5036,"t":"יָדֶֽיהָ","p":"ידיה","c":16,"v":9},{"id":5037,"t":"וַיֹּ֤אמֶר","p":"ויאמר","c":16,"v":10},{"id":5038,"t":"לָהּ֙","p":"לה","c":16,"v":10},{"id":5039,"t":"מַלְאַ֣ךְ","p":"מלאך","c":16,"v":10},{"id":5040,"t":"יְהֹוָ֔ה","p":"יהוה","c":16,"v":10},{"id":5041,"t":"הַרְבָּ֥ה","p":"הרבה","c":16,"v":10},{"id":5042,"t":"אַרְבֶּ֖ה","p":"ארבה","c":16,"v":10},{"id":5043,"t":"אֶת","p":"את","c":16,"v":10},{"id":5044,"t":"זַרְעֵ֑ךְ","p":"זרעך","c":16,"v":10},{"id":5045,"t":"וְלֹ֥א","p":"ולא","c":16,"v":10},{"id":5046,"t":"יִסָּפֵ֖ר","p":"יספר","c":16,"v":10},{"id":5047,"t":"מֵרֹֽב","p":"מרב","c":16,"v":10},{"id":5048,"t":"וַיֹּ֤אמֶר","p":"ויאמר","c":16,"v":11},{"id":5049,"t":"לָהּ֙","p":"לה","c":16,"v":11},{"id":5050,"t":"מַלְאַ֣ךְ","p":"מלאך","c":16,"v":11},{"id":5051,"t":"יְהֹוָ֔ה","p":"יהוה","c":16,"v":11},{"id":5052,"t":"הִנָּ֥ךְ","p":"הנך","c":16,"v":11},{"id":5053,"t":"הָרָ֖ה","p":"הרה","c":16,"v":11},{"id":5054,"t":"וְיֹלַ֣דְתְּ","p":"וילדת","c":16,"v":11},{"id":5055,"t":"בֵּ֑ן","p":"בן","c":16,"v":11},{"id":5056,"t":"וְקָרָ֤את","p":"וקראת","c":16,"v":11},{"id":5057,"t":"שְׁמוֹ֙","p":"שמו","c":16,"v":11},{"id":5058,"t":"יִשְׁמָעֵ֔אל","p":"ישמעאל","c":16,"v":11},{"id":5059,"t":"כִּֽי","p":"כי","c":16,"v":11},{"id":5060,"t":"שָׁמַ֥ע","p":"שמע","c":16,"v":11},{"id":5061,"t":"יְהֹוָ֖ה","p":"יהוה","c":16,"v":11},{"id":5062,"t":"אֶל","p":"אל","c":16,"v":11},{"id":5063,"t":"עׇנְיֵֽךְ","p":"עניך","c":16,"v":11},{"id":5064,"t":"וְה֤וּא","p":"והוא","c":16,"v":12},{"id":5065,"t":"יִהְיֶה֙","p":"יהיה","c":16,"v":12},{"id":5066,"t":"פֶּ֣רֶא","p":"פרא","c":16,"v":12},{"id":5067,"t":"אָדָ֔ם","p":"אדם","c":16,"v":12},{"id":5068,"t":"יָד֣וֹ","p":"ידו","c":16,"v":12},{"id":5069,"t":"בַכֹּ֔ל","p":"בכל","c":16,"v":12},{"id":5070,"t":"וְיַ֥ד","p":"ויד","c":16,"v":12},{"id":5071,"t":"כֹּ֖ל","p":"כל","c":16,"v":12},{"id":5072,"t":"בּ֑וֹ","p":"בו","c":16,"v":12},{"id":5073,"t":"וְעַל","p":"ועל","c":16,"v":12},{"id":5074,"t":"פְּנֵ֥י","p":"פני","c":16,"v":12},{"id":5075,"t":"כׇל","p":"כל","c":16,"v":12},{"id":5076,"t":"אֶחָ֖יו","p":"אחיו","c":16,"v":12},{"id":5077,"t":"יִשְׁכֹּֽן","p":"ישכן","c":16,"v":12},{"id":5078,"t":"וַתִּקְרָ֤א","p":"ותקרא","c":16,"v":13},{"id":5079,"t":"שֵׁם","p":"שם","c":16,"v":13},{"id":5080,"t":"יְהֹוָה֙","p":"יהוה","c":16,"v":13},{"id":5081,"t":"הַדֹּבֵ֣ר","p":"הדבר","c":16,"v":13},{"id":5082,"t":"אֵלֶ֔יהָ","p":"אליה","c":16,"v":13},{"id":5083,"t":"אַתָּ֖ה","p":"אתה","c":16,"v":13},{"id":5084,"t":"אֵ֣ל","p":"אל","c":16,"v":13},{"id":5085,"t":"רֳאִ֑י","p":"ראי","c":16,"v":13},{"id":5086,"t":"כִּ֣י","p":"כי","c":16,"v":13},{"id":5087,"t":"אָֽמְרָ֗ה","p":"אמרה","c":16,"v":13},{"id":5088,"t":"הֲגַ֥ם","p":"הגם","c":16,"v":13},{"id":5089,"t":"הֲלֹ֛ם","p":"הלם","c":16,"v":13},{"id":5090,"t":"רָאִ֖יתִי","p":"ראיתי","c":16,"v":13},{"id":5091,"t":"אַחֲרֵ֥י","p":"אחרי","c":16,"v":13},{"id":5092,"t":"רֹאִֽי","p":"ראי","c":16,"v":13},{"id":5093,"t":"עַל","p":"על","c":16,"v":14},{"id":5094,"t":"כֵּן֙","p":"כן","c":16,"v":14},{"id":5095,"t":"קָרָ֣א","p":"קרא","c":16,"v":14},{"id":5096,"t":"לַבְּאֵ֔ר","p":"לבאר","c":16,"v":14},{"id":5097,"t":"בְּאֵ֥ר","p":"באר","c":16,"v":14},{"id":5098,"t":"לַחַ֖י","p":"לחי","c":16,"v":14},{"id":5099,"t":"רֹאִ֑י","p":"ראי","c":16,"v":14},{"id":5100,"t":"הִנֵּ֥ה","p":"הנה","c":16,"v":14},{"id":5101,"t":"בֵין","p":"בין","c":16,"v":14},{"id":5102,"t":"קָדֵ֖שׁ","p":"קדש","c":16,"v":14},{"id":5103,"t":"וּבֵ֥ין","p":"ובין","c":16,"v":14},{"id":5104,"t":"בָּֽרֶד","p":"ברד","c":16,"v":14},{"id":5105,"t":"וַתֵּ֧לֶד","p":"ותלד","c":16,"v":15},{"id":5106,"t":"הָגָ֛ר","p":"הגר","c":16,"v":15},{"id":5107,"t":"לְאַבְרָ֖ם","p":"לאברם","c":16,"v":15},{"id":5108,"t":"בֵּ֑ן","p":"בן","c":16,"v":15},{"id":5109,"t":"וַיִּקְרָ֨א","p":"ויקרא","c":16,"v":15},{"id":5110,"t":"אַבְרָ֧ם","p":"אברם","c":16,"v":15},{"id":5111,"t":"שֶׁם","p":"שם","c":16,"v":15},{"id":5112,"t":"בְּנ֛וֹ","p":"בנו","c":16,"v":15},{"id":5113,"t":"אֲשֶׁר","p":"אשר","c":16,"v":15},{"id":5114,"t":"יָלְדָ֥ה","p":"ילדה","c":16,"v":15},{"id":5115,"t":"הָגָ֖ר","p":"הגר","c":16,"v":15},{"id":5116,"t":"יִשְׁמָעֵֽאל","p":"ישמעאל","c":16,"v":15},{"id":5117,"t":"וְאַבְרָ֕ם","p":"ואברם","c":16,"v":16},{"id":5118,"t":"בֶּן","p":"בן","c":16,"v":16},{"id":5119,"t":"שְׁמֹנִ֥ים","p":"שמנים","c":16,"v":16},{"id":5120,"t":"שָׁנָ֖ה","p":"שנה","c":16,"v":16},{"id":5121,"t":"וְשֵׁ֣שׁ","p":"ושש","c":16,"v":16},{"id":5122,"t":"שָׁנִ֑ים","p":"שנים","c":16,"v":16},{"id":5123,"t":"בְּלֶֽדֶת","p":"בלדת","c":16,"v":16},{"id":5124,"t":"הָגָ֥ר","p":"הגר","c":16,"v":16},{"id":5125,"t":"אֶת","p":"את","c":16,"v":16},{"id":5126,"t":"יִשְׁמָעֵ֖אל","p":"ישמעאל","c":16,"v":16},{"id":5127,"t":"לְאַבְרָֽם","p":"לאברם","c":16,"v":16},{"id":5128,"t":"וַיְהִ֣י","p":"ויהי","c":17,"v":1},{"id":5129,"t":"אַבְרָ֔ם","p":"אברם","c":17,"v":1},{"id":5130,"t":"בֶּן","p":"בן","c":17,"v":1},{"id":5131,"t":"תִּשְׁעִ֥ים","p":"תשעים","c":17,"v":1},{"id":5132,"t":"שָׁנָ֖ה","p":"שנה","c":17,"v":1},{"id":5133,"t":"וְתֵ֣שַׁע","p":"ותשע","c":17,"v":1},{"id":5134,"t":"שָׁנִ֑ים","p":"שנים","c":17,"v":1},{"id":5135,"t":"וַיֵּרָ֨א","p":"וירא","c":17,"v":1},{"id":5136,"t":"יְהֹוָ֜ה","p":"יהוה","c":17,"v":1},{"id":5137,"t":"אֶל","p":"אל","c":17,"v":1},{"id":5138,"t":"אַבְרָ֗ם","p":"אברם","c":17,"v":1},{"id":5139,"t":"וַיֹּ֤אמֶר","p":"ויאמר","c":17,"v":1},{"id":5140,"t":"אֵלָיו֙","p":"אליו","c":17,"v":1},{"id":5141,"t":"אֲנִי","p":"אני","c":17,"v":1},{"id":5142,"t":"אֵ֣ל","p":"אל","c":17,"v":1},{"id":5143,"t":"שַׁדַּ֔י","p":"שדי","c":17,"v":1},{"id":5144,"t":"הִתְהַלֵּ֥ךְ","p":"התהלך","c":17,"v":1},{"id":5145,"t":"לְפָנַ֖י","p":"לפני","c":17,"v":1},{"id":5146,"t":"וֶהְיֵ֥ה","p":"והיה","c":17,"v":1},{"id":5147,"t":"תָמִֽים","p":"תמים","c":17,"v":1},{"id":5148,"t":"וְאֶתְּנָ֥ה","p":"ואתנה","c":17,"v":2},{"id":5149,"t":"בְרִיתִ֖י","p":"בריתי","c":17,"v":2},{"id":5150,"t":"בֵּינִ֣י","p":"ביני","c":17,"v":2},{"id":5151,"t":"וּבֵינֶ֑ךָ","p":"ובינך","c":17,"v":2},{"id":5152,"t":"וְאַרְבֶּ֥ה","p":"וארבה","c":17,"v":2},{"id":5153,"t":"אוֹתְךָ֖","p":"אותך","c":17,"v":2},{"id":5154,"t":"בִּמְאֹ֥ד","p":"במאד","c":17,"v":2},{"id":5155,"t":"מְאֹֽד","p":"מאד","c":17,"v":2},{"id":5156,"t":"וַיִּפֹּ֥ל","p":"ויפל","c":17,"v":3},{"id":5157,"t":"אַבְרָ֖ם","p":"אברם","c":17,"v":3},{"id":5158,"t":"עַל","p":"על","c":17,"v":3},{"id":5159,"t":"פָּנָ֑יו","p":"פניו","c":17,"v":3},{"id":5160,"t":"וַיְדַבֵּ֥ר","p":"וידבר","c":17,"v":3},{"id":5161,"t":"אִתּ֛וֹ","p":"אתו","c":17,"v":3},{"id":5162,"t":"אֱלֹהִ֖ים","p":"אלהים","c":17,"v":3},{"id":5163,"t":"לֵאמֹֽר","p":"לאמר","c":17,"v":3},{"id":5164,"t":"אֲנִ֕י","p":"אני","c":17,"v":4},{"id":5165,"t":"הִנֵּ֥ה","p":"הנה","c":17,"v":4},{"id":5166,"t":"בְרִיתִ֖י","p":"בריתי","c":17,"v":4},{"id":5167,"t":"אִתָּ֑ךְ","p":"אתך","c":17,"v":4},{"id":5168,"t":"וְהָיִ֕יתָ","p":"והיית","c":17,"v":4},{"id":5169,"t":"לְאַ֖ב","p":"לאב","c":17,"v":4},{"id":5170,"t":"הֲמ֥וֹן","p":"המון","c":17,"v":4},{"id":5171,"t":"גּוֹיִֽם","p":"גוים","c":17,"v":4},{"id":5172,"t":"וְלֹא","p":"ולא","c":17,"v":5},{"id":5173,"t":"יִקָּרֵ֥א","p":"יקרא","c":17,"v":5},{"id":5174,"t":"ע֛וֹד","p":"עוד","c":17,"v":5},{"id":5175,"t":"אֶת","p":"את","c":17,"v":5},{"id":5176,"t":"שִׁמְךָ֖","p":"שמך","c":17,"v":5},{"id":5177,"t":"אַבְרָ֑ם","p":"אברם","c":17,"v":5},{"id":5178,"t":"וְהָיָ֤ה","p":"והיה","c":17,"v":5},{"id":5179,"t":"שִׁמְךָ֙","p":"שמך","c":17,"v":5},{"id":5180,"t":"אַבְרָהָ֔ם","p":"אברהם","c":17,"v":5},{"id":5181,"t":"כִּ֛י","p":"כי","c":17,"v":5},{"id":5182,"t":"אַב","p":"אב","c":17,"v":5},{"id":5183,"t":"הֲמ֥וֹן","p":"המון","c":17,"v":5},{"id":5184,"t":"גּוֹיִ֖ם","p":"גוים","c":17,"v":5},{"id":5185,"t":"נְתַתִּֽיךָ","p":"נתתיך","c":17,"v":5},{"id":5186,"t":"וְהִפְרֵתִ֤י","p":"והפרתי","c":17,"v":6},{"id":5187,"t":"אֹֽתְךָ֙","p":"אתך","c":17,"v":6},{"id":5188,"t":"בִּמְאֹ֣ד","p":"במאד","c":17,"v":6},{"id":5189,"t":"מְאֹ֔ד","p":"מאד","c":17,"v":6},{"id":5190,"t":"וּנְתַתִּ֖יךָ","p":"ונתתיך","c":17,"v":6},{"id":5191,"t":"לְגוֹיִ֑ם","p":"לגוים","c":17,"v":6},{"id":5192,"t":"וּמְלָכִ֖ים","p":"ומלכים","c":17,"v":6},{"id":5193,"t":"מִמְּךָ֥","p":"ממך","c":17,"v":6},{"id":5194,"t":"יֵצֵֽאוּ","p":"יצאו","c":17,"v":6},{"id":5195,"t":"וַהֲקִמֹתִ֨י","p":"והקמתי","c":17,"v":7},{"id":5196,"t":"אֶת","p":"את","c":17,"v":7},{"id":5197,"t":"בְּרִיתִ֜י","p":"בריתי","c":17,"v":7},{"id":5198,"t":"בֵּינִ֣י","p":"ביני","c":17,"v":7},{"id":5199,"t":"וּבֵינֶ֗ךָ","p":"ובינך","c":17,"v":7},{"id":5200,"t":"וּבֵ֨ין","p":"ובין","c":17,"v":7},{"id":5201,"t":"זַרְעֲךָ֧","p":"זרעך","c":17,"v":7},{"id":5202,"t":"אַחֲרֶ֛יךָ","p":"אחריך","c":17,"v":7},{"id":5203,"t":"לְדֹרֹתָ֖ם","p":"לדרתם","c":17,"v":7},{"id":5204,"t":"לִבְרִ֣ית","p":"לברית","c":17,"v":7},{"id":5205,"t":"עוֹלָ֑ם","p":"עולם","c":17,"v":7},{"id":5206,"t":"לִהְי֤וֹת","p":"להיות","c":17,"v":7},{"id":5207,"t":"לְךָ֙","p":"לך","c":17,"v":7},{"id":5208,"t":"לֵֽאלֹהִ֔ים","p":"לאלהים","c":17,"v":7},{"id":5209,"t":"וּֽלְזַרְעֲךָ֖","p":"ולזרעך","c":17,"v":7},{"id":5210,"t":"אַחֲרֶֽיךָ","p":"אחריך","c":17,"v":7},{"id":5211,"t":"וְנָתַתִּ֣י","p":"ונתתי","c":17,"v":8},{"id":5212,"t":"לְ֠ךָ֠","p":"לך","c":17,"v":8},{"id":5213,"t":"וּלְזַרְעֲךָ֨","p":"ולזרעך","c":17,"v":8},{"id":5214,"t":"אַחֲרֶ֜יךָ","p":"אחריך","c":17,"v":8},{"id":5215,"t":"אֵ֣ת","p":"את","c":17,"v":8},{"id":5216,"t":"׀","p":"ארץ","c":17,"v":8},{"id":5217,"t":"אֶ֣רֶץ","p":"מגריך","c":17,"v":8},{"id":5218,"t":"מְגֻרֶ֗יךָ","p":"את","c":17,"v":8},{"id":5219,"t":"אֵ֚ת","p":"כל","c":17,"v":8},{"id":5220,"t":"כׇּל","p":"ארץ","c":17,"v":8},{"id":5221,"t":"אֶ֣רֶץ","p":"כנען","c":17,"v":8},{"id":5222,"t":"כְּנַ֔עַן","p":"לאחזת","c":17,"v":8},{"id":5223,"t":"לַאֲחֻזַּ֖ת","p":"עולם","c":17,"v":8},{"id":5224,"t":"עוֹלָ֑ם","p":"והייתי","c":17,"v":8},{"id":5225,"t":"וְהָיִ֥יתִי","p":"להם","c":17,"v":8},{"id":5226,"t":"לָהֶ֖ם","p":"לאלהים","c":17,"v":8},{"id":5227,"t":"וַיֹּ֤אמֶר","p":"ויאמר","c":17,"v":9},{"id":5228,"t":"אֱלֹהִים֙","p":"אלהים","c":17,"v":9},{"id":5229,"t":"אֶל","p":"אל","c":17,"v":9},{"id":5230,"t":"אַבְרָהָ֔ם","p":"אברהם","c":17,"v":9},{"id":5231,"t":"וְאַתָּ֖ה","p":"ואתה","c":17,"v":9},{"id":5232,"t":"אֶת","p":"את","c":17,"v":9},{"id":5233,"t":"בְּרִיתִ֣י","p":"בריתי","c":17,"v":9},{"id":5234,"t":"תִשְׁמֹ֑ר","p":"תשמר","c":17,"v":9},{"id":5235,"t":"אַתָּ֛ה","p":"אתה","c":17,"v":9},{"id":5236,"t":"וְזַרְעֲךָ֥","p":"וזרעך","c":17,"v":9},{"id":5237,"t":"אַֽחֲרֶ֖יךָ","p":"אחריך","c":17,"v":9},{"id":5238,"t":"לְדֹרֹתָֽם","p":"לדרתם","c":17,"v":9},{"id":5239,"t":"זֹ֣את","p":"זאת","c":17,"v":10},{"id":5240,"t":"בְּרִיתִ֞י","p":"בריתי","c":17,"v":10},{"id":5241,"t":"אֲשֶׁ֣ר","p":"אשר","c":17,"v":10},{"id":5242,"t":"תִּשְׁמְר֗וּ","p":"תשמרו","c":17,"v":10},{"id":5243,"t":"בֵּינִי֙","p":"ביני","c":17,"v":10},{"id":5244,"t":"וּבֵ֣ינֵיכֶ֔ם","p":"וביניכם","c":17,"v":10},{"id":5245,"t":"וּבֵ֥ין","p":"ובין","c":17,"v":10},{"id":5246,"t":"זַרְעֲךָ֖","p":"זרעך","c":17,"v":10},{"id":5247,"t":"אַחֲרֶ֑יךָ","p":"אחריך","c":17,"v":10},{"id":5248,"t":"הִמּ֥וֹל","p":"המול","c":17,"v":10},{"id":5249,"t":"לָכֶ֖ם","p":"לכם","c":17,"v":10},{"id":5250,"t":"כׇּל","p":"כל","c":17,"v":10},{"id":5251,"t":"זָכָֽר","p":"זכר","c":17,"v":10},{"id":5252,"t":"וּנְמַלְתֶּ֕ם","p":"ונמלתם","c":17,"v":11},{"id":5253,"t":"אֵ֖ת","p":"את","c":17,"v":11},{"id":5254,"t":"בְּשַׂ֣ר","p":"בשר","c":17,"v":11},{"id":5255,"t":"עׇרְלַתְכֶ֑ם","p":"ערלתכם","c":17,"v":11},{"id":5256,"t":"וְהָיָה֙","p":"והיה","c":17,"v":11},{"id":5257,"t":"לְא֣וֹת","p":"לאות","c":17,"v":11},{"id":5258,"t":"בְּרִ֔ית","p":"ברית","c":17,"v":11},{"id":5259,"t":"בֵּינִ֖י","p":"ביני","c":17,"v":11},{"id":5260,"t":"וּבֵינֵיכֶֽם","p":"וביניכם","c":17,"v":11},{"id":5261,"t":"וּבֶן","p":"ובן","c":17,"v":12},{"id":5262,"t":"שְׁמֹנַ֣ת","p":"שמנת","c":17,"v":12},{"id":5263,"t":"יָמִ֗ים","p":"ימים","c":17,"v":12},{"id":5264,"t":"יִמּ֥וֹל","p":"ימול","c":17,"v":12},{"id":5265,"t":"לָכֶ֛ם","p":"לכם","c":17,"v":12},{"id":5266,"t":"כׇּל","p":"כל","c":17,"v":12},{"id":5267,"t":"זָכָ֖ר","p":"זכר","c":17,"v":12},{"id":5268,"t":"לְדֹרֹתֵיכֶ֑ם","p":"לדרתיכם","c":17,"v":12},{"id":5269,"t":"יְלִ֣יד","p":"יליד","c":17,"v":12},{"id":5270,"t":"בָּ֔יִת","p":"בית","c":17,"v":12},{"id":5271,"t":"וּמִקְנַת","p":"ומקנת","c":17,"v":12},{"id":5272,"t":"כֶּ֙סֶף֙","p":"כסף","c":17,"v":12},{"id":5273,"t":"מִכֹּ֣ל","p":"מכל","c":17,"v":12},{"id":5274,"t":"בֶּן","p":"בן","c":17,"v":12},{"id":5275,"t":"נֵכָ֔ר","p":"נכר","c":17,"v":12},{"id":5276,"t":"אֲשֶׁ֛ר","p":"אשר","c":17,"v":12},{"id":5277,"t":"לֹ֥א","p":"לא","c":17,"v":12},{"id":5278,"t":"מִֽזַּרְעֲךָ֖","p":"מזרעך","c":17,"v":12},{"id":5279,"t":"הֽוּא","p":"הוא","c":17,"v":12},{"id":5280,"t":"הִמּ֧וֹל","p":"המול","c":17,"v":13},{"id":5281,"t":"׀","p":"ימול","c":17,"v":13},{"id":5282,"t":"יִמּ֛וֹל","p":"יליד","c":17,"v":13},{"id":5283,"t":"יְלִ֥יד","p":"ביתך","c":17,"v":13},{"id":5284,"t":"בֵּֽיתְךָ֖","p":"ומקנת","c":17,"v":13},{"id":5285,"t":"וּמִקְנַ֣ת","p":"כספך","c":17,"v":13},{"id":5286,"t":"כַּסְפֶּ֑ךָ","p":"והיתה","c":17,"v":13},{"id":5287,"t":"וְהָיְתָ֧ה","p":"בריתי","c":17,"v":13},{"id":5288,"t":"בְרִיתִ֛י","p":"בבשרכם","c":17,"v":13},{"id":5289,"t":"בִּבְשַׂרְכֶ֖ם","p":"לברית","c":17,"v":13},{"id":5290,"t":"לִבְרִ֥ית","p":"עולם","c":17,"v":13},{"id":5291,"t":"וְעָרֵ֣ל","p":"וערל","c":17,"v":14},{"id":5292,"t":"׀","p":"זכר","c":17,"v":14},{"id":5293,"t":"זָכָ֗ר","p":"אשר","c":17,"v":14},{"id":5294,"t":"אֲשֶׁ֤ר","p":"לא","c":17,"v":14},{"id":5295,"t":"לֹֽא","p":"ימול","c":17,"v":14},{"id":5296,"t":"יִמּוֹל֙","p":"את","c":17,"v":14},{"id":5297,"t":"אֶת","p":"בשר","c":17,"v":14},{"id":5298,"t":"בְּשַׂ֣ר","p":"ערלתו","c":17,"v":14},{"id":5299,"t":"עׇרְלָת֔וֹ","p":"ונכרתה","c":17,"v":14},{"id":5300,"t":"וְנִכְרְתָ֛ה","p":"הנפש","c":17,"v":14},{"id":5301,"t":"הַנֶּ֥פֶשׁ","p":"ההוא","c":17,"v":14},{"id":5302,"t":"הַהִ֖וא","p":"מעמיה","c":17,"v":14},{"id":5303,"t":"מֵעַמֶּ֑יהָ","p":"את","c":17,"v":14},{"id":5304,"t":"אֶת","p":"בריתי","c":17,"v":14},{"id":5305,"t":"בְּרִיתִ֖י","p":"הפר","c":17,"v":14},{"id":5306,"t":"וַיֹּ֤אמֶר","p":"ויאמר","c":17,"v":15},{"id":5307,"t":"אֱלֹהִים֙","p":"אלהים","c":17,"v":15},{"id":5308,"t":"אֶל","p":"אל","c":17,"v":15},{"id":5309,"t":"אַבְרָהָ֔ם","p":"אברהם","c":17,"v":15},{"id":5310,"t":"שָׂרַ֣י","p":"שרי","c":17,"v":15},{"id":5311,"t":"אִשְׁתְּךָ֔","p":"אשתך","c":17,"v":15},{"id":5312,"t":"לֹא","p":"לא","c":17,"v":15},{"id":5313,"t":"תִקְרָ֥א","p":"תקרא","c":17,"v":15},{"id":5314,"t":"אֶת","p":"את","c":17,"v":15},{"id":5315,"t":"שְׁמָ֖הּ","p":"שמה","c":17,"v":15},{"id":5316,"t":"שָׂרָ֑י","p":"שרי","c":17,"v":15},{"id":5317,"t":"כִּ֥י","p":"כי","c":17,"v":15},{"id":5318,"t":"שָׂרָ֖ה","p":"שרה","c":17,"v":15},{"id":5319,"t":"שְׁמָֽהּ","p":"שמה","c":17,"v":15},{"id":5320,"t":"וּבֵרַכְתִּ֣י","p":"וברכתי","c":17,"v":16},{"id":5321,"t":"אֹתָ֔הּ","p":"אתה","c":17,"v":16},{"id":5322,"t":"וְגַ֨ם","p":"וגם","c":17,"v":16},{"id":5323,"t":"נָתַ֧תִּי","p":"נתתי","c":17,"v":16},{"id":5324,"t":"מִמֶּ֛נָּה","p":"ממנה","c":17,"v":16},{"id":5325,"t":"לְךָ֖","p":"לך","c":17,"v":16},{"id":5326,"t":"בֵּ֑ן","p":"בן","c":17,"v":16},{"id":5327,"t":"וּבֵֽרַכְתִּ֙יהָ֙","p":"וברכתיה","c":17,"v":16},{"id":5328,"t":"וְהָֽיְתָ֣ה","p":"והיתה","c":17,"v":16},{"id":5329,"t":"לְגוֹיִ֔ם","p":"לגוים","c":17,"v":16},{"id":5330,"t":"מַלְכֵ֥י","p":"מלכי","c":17,"v":16},{"id":5331,"t":"עַמִּ֖ים","p":"עמים","c":17,"v":16},{"id":5332,"t":"מִמֶּ֥נָּה","p":"ממנה","c":17,"v":16},{"id":5333,"t":"יִהְיֽוּ","p":"יהיו","c":17,"v":16},{"id":5334,"t":"וַיִּפֹּ֧ל","p":"ויפל","c":17,"v":17},{"id":5335,"t":"אַבְרָהָ֛ם","p":"אברהם","c":17,"v":17},{"id":5336,"t":"עַל","p":"על","c":17,"v":17},{"id":5337,"t":"פָּנָ֖יו","p":"פניו","c":17,"v":17},{"id":5338,"t":"וַיִּצְחָ֑ק","p":"ויצחק","c":17,"v":17},{"id":5339,"t":"וַיֹּ֣אמֶר","p":"ויאמר","c":17,"v":17},{"id":5340,"t":"בְּלִבּ֗וֹ","p":"בלבו","c":17,"v":17},{"id":5341,"t":"הַלְּבֶ֤ן","p":"הלבן","c":17,"v":17},{"id":5342,"t":"מֵאָֽה","p":"מאה","c":17,"v":17},{"id":5343,"t":"שָׁנָה֙","p":"שנה","c":17,"v":17},{"id":5344,"t":"יִוָּלֵ֔ד","p":"יולד","c":17,"v":17},{"id":5345,"t":"וְאִ֨ם","p":"ואם","c":17,"v":17},{"id":5346,"t":"שָׂרָ֔ה","p":"שרה","c":17,"v":17},{"id":5347,"t":"הֲבַת","p":"הבת","c":17,"v":17},{"id":5348,"t":"תִּשְׁעִ֥ים","p":"תשעים","c":17,"v":17},{"id":5349,"t":"שָׁנָ֖ה","p":"שנה","c":17,"v":17},{"id":5350,"t":"תֵּלֵֽד","p":"תלד","c":17,"v":17},{"id":5351,"t":"וַיֹּ֥אמֶר","p":"ויאמר","c":17,"v":18},{"id":5352,"t":"אַבְרָהָ֖ם","p":"אברהם","c":17,"v":18},{"id":5353,"t":"אֶל","p":"אל","c":17,"v":18},{"id":5354,"t":"הָֽאֱלֹהִ֑ים","p":"האלהים","c":17,"v":18},{"id":5355,"t":"ל֥וּ","p":"לו","c":17,"v":18},{"id":5356,"t":"יִשְׁמָעֵ֖אל","p":"ישמעאל","c":17,"v":18},{"id":5357,"t":"יִחְיֶ֥ה","p":"יחיה","c":17,"v":18},{"id":5358,"t":"לְפָנֶֽיךָ","p":"לפניך","c":17,"v":18},{"id":5359,"t":"וַיֹּ֣אמֶר","p":"ויאמר","c":17,"v":19},{"id":5360,"t":"אֱלֹהִ֗ים","p":"אלהים","c":17,"v":19},{"id":5361,"t":"אֲבָל֙","p":"אבל","c":17,"v":19},{"id":5362,"t":"שָׂרָ֣ה","p":"שרה","c":17,"v":19},{"id":5363,"t":"אִשְׁתְּךָ֗","p":"אשתך","c":17,"v":19},{"id":5364,"t":"יֹלֶ֤דֶת","p":"ילדת","c":17,"v":19},{"id":5365,"t":"לְךָ֙","p":"לך","c":17,"v":19},{"id":5366,"t":"בֵּ֔ן","p":"בן","c":17,"v":19},{"id":5367,"t":"וְקָרָ֥אתָ","p":"וקראת","c":17,"v":19},{"id":5368,"t":"אֶת","p":"את","c":17,"v":19},{"id":5369,"t":"שְׁמ֖וֹ","p":"שמו","c":17,"v":19},{"id":5370,"t":"יִצְחָ֑ק","p":"יצחק","c":17,"v":19},{"id":5371,"t":"וַהֲקִמֹתִ֨י","p":"והקמתי","c":17,"v":19},{"id":5372,"t":"אֶת","p":"את","c":17,"v":19},{"id":5373,"t":"בְּרִיתִ֥י","p":"בריתי","c":17,"v":19},{"id":5374,"t":"אִתּ֛וֹ","p":"אתו","c":17,"v":19},{"id":5375,"t":"לִבְרִ֥ית","p":"לברית","c":17,"v":19},{"id":5376,"t":"עוֹלָ֖ם","p":"עולם","c":17,"v":19},{"id":5377,"t":"לְזַרְע֥וֹ","p":"לזרעו","c":17,"v":19},{"id":5378,"t":"אַחֲרָֽיו","p":"אחריו","c":17,"v":19},{"id":5379,"t":"וּֽלְיִשְׁמָעֵאל֮","p":"ולישמעאל","c":17,"v":20},{"id":5380,"t":"שְׁמַעְתִּ֒יךָ֒","p":"שמעתיך","c":17,"v":20},{"id":5381,"t":"הִנֵּ֣ה","p":"הנה","c":17,"v":20},{"id":5382,"t":"׀","p":"ברכתי","c":17,"v":20},{"id":5383,"t":"בֵּרַ֣כְתִּי","p":"אתו","c":17,"v":20},{"id":5384,"t":"אֹת֗וֹ","p":"והפריתי","c":17,"v":20},{"id":5385,"t":"וְהִפְרֵיתִ֥י","p":"אתו","c":17,"v":20},{"id":5386,"t":"אֹת֛וֹ","p":"והרביתי","c":17,"v":20},{"id":5387,"t":"וְהִרְבֵּיתִ֥י","p":"אתו","c":17,"v":20},{"id":5388,"t":"אֹת֖וֹ","p":"במאד","c":17,"v":20},{"id":5389,"t":"בִּמְאֹ֣ד","p":"מאד","c":17,"v":20},{"id":5390,"t":"מְאֹ֑ד","p":"שנים","c":17,"v":20},{"id":5391,"t":"שְׁנֵים","p":"עשר","c":17,"v":20},{"id":5392,"t":"עָשָׂ֤ר","p":"נשיאם","c":17,"v":20},{"id":5393,"t":"נְשִׂיאִם֙","p":"יוליד","c":17,"v":20},{"id":5394,"t":"יוֹלִ֔יד","p":"ונתתיו","c":17,"v":20},{"id":5395,"t":"וּנְתַתִּ֖יו","p":"לגוי","c":17,"v":20},{"id":5396,"t":"לְג֥וֹי","p":"גדול","c":17,"v":20},{"id":5397,"t":"וְאֶת","p":"ואת","c":17,"v":21},{"id":5398,"t":"בְּרִיתִ֖י","p":"בריתי","c":17,"v":21},{"id":5399,"t":"אָקִ֣ים","p":"אקים","c":17,"v":21},{"id":5400,"t":"אֶת","p":"את","c":17,"v":21},{"id":5401,"t":"יִצְחָ֑ק","p":"יצחק","c":17,"v":21},{"id":5402,"t":"אֲשֶׁר֩","p":"אשר","c":17,"v":21},{"id":5403,"t":"תֵּלֵ֨ד","p":"תלד","c":17,"v":21},{"id":5404,"t":"לְךָ֤","p":"לך","c":17,"v":21},{"id":5405,"t":"שָׂרָה֙","p":"שרה","c":17,"v":21},{"id":5406,"t":"לַמּוֹעֵ֣ד","p":"למועד","c":17,"v":21},{"id":5407,"t":"הַזֶּ֔ה","p":"הזה","c":17,"v":21},{"id":5408,"t":"בַּשָּׁנָ֖ה","p":"בשנה","c":17,"v":21},{"id":5409,"t":"הָאַחֶֽרֶת","p":"האחרת","c":17,"v":21},{"id":5410,"t":"וַיְכַ֖ל","p":"ויכל","c":17,"v":22},{"id":5411,"t":"לְדַבֵּ֣ר","p":"לדבר","c":17,"v":22},{"id":5412,"t":"אִתּ֑וֹ","p":"אתו","c":17,"v":22},{"id":5413,"t":"וַיַּ֣עַל","p":"ויעל","c":17,"v":22},{"id":5414,"t":"אֱלֹהִ֔ים","p":"אלהים","c":17,"v":22},{"id":5415,"t":"מֵעַ֖ל","p":"מעל","c":17,"v":22},{"id":5416,"t":"אַבְרָהָֽם","p":"אברהם","c":17,"v":22},{"id":5417,"t":"וַיִּקַּ֨ח","p":"ויקח","c":17,"v":23},{"id":5418,"t":"אַבְרָהָ֜ם","p":"אברהם","c":17,"v":23},{"id":5419,"t":"אֶת","p":"את","c":17,"v":23},{"id":5420,"t":"יִשְׁמָעֵ֣אל","p":"ישמעאל","c":17,"v":23},{"id":5421,"t":"בְּנ֗וֹ","p":"בנו","c":17,"v":23},{"id":5422,"t":"וְאֵ֨ת","p":"ואת","c":17,"v":23},{"id":5423,"t":"כׇּל","p":"כל","c":17,"v":23},{"id":5424,"t":"יְלִידֵ֤י","p":"ילידי","c":17,"v":23},{"id":5425,"t":"בֵיתוֹ֙","p":"ביתו","c":17,"v":23},{"id":5426,"t":"וְאֵת֙","p":"ואת","c":17,"v":23},{"id":5427,"t":"כׇּל","p":"כל","c":17,"v":23},{"id":5428,"t":"מִקְנַ֣ת","p":"מקנת","c":17,"v":23},{"id":5429,"t":"כַּסְפּ֔וֹ","p":"כספו","c":17,"v":23},{"id":5430,"t":"כׇּל","p":"כל","c":17,"v":23},{"id":5431,"t":"זָכָ֕ר","p":"זכר","c":17,"v":23},{"id":5432,"t":"בְּאַנְשֵׁ֖י","p":"באנשי","c":17,"v":23},{"id":5433,"t":"בֵּ֣ית","p":"בית","c":17,"v":23},{"id":5434,"t":"אַבְרָהָ֑ם","p":"אברהם","c":17,"v":23},{"id":5435,"t":"וַיָּ֜מׇל","p":"וימל","c":17,"v":23},{"id":5436,"t":"אֶת","p":"את","c":17,"v":23},{"id":5437,"t":"בְּשַׂ֣ר","p":"בשר","c":17,"v":23},{"id":5438,"t":"עׇרְלָתָ֗ם","p":"ערלתם","c":17,"v":23},{"id":5439,"t":"בְּעֶ֙צֶם֙","p":"בעצם","c":17,"v":23},{"id":5440,"t":"הַיּ֣וֹם","p":"היום","c":17,"v":23},{"id":5441,"t":"הַזֶּ֔ה","p":"הזה","c":17,"v":23},{"id":5442,"t":"כַּאֲשֶׁ֛ר","p":"כאשר","c":17,"v":23},{"id":5443,"t":"דִּבֶּ֥ר","p":"דבר","c":17,"v":23},{"id":5444,"t":"אִתּ֖וֹ","p":"אתו","c":17,"v":23},{"id":5445,"t":"אֱלֹהִֽים","p":"אלהים","c":17,"v":23},{"id":5446,"t":"וְאַ֨בְרָהָ֔ם","p":"ואברהם","c":17,"v":24},{"id":5447,"t":"בֶּן","p":"בן","c":17,"v":24},{"id":5448,"t":"תִּשְׁעִ֥ים","p":"תשעים","c":17,"v":24},{"id":5449,"t":"וָתֵ֖שַׁע","p":"ותשע","c":17,"v":24},{"id":5450,"t":"שָׁנָ֑ה","p":"שנה","c":17,"v":24},{"id":5451,"t":"בְּהִמֹּל֖וֹ","p":"בהמלו","c":17,"v":24},{"id":5452,"t":"בְּשַׂ֥ר","p":"בשר","c":17,"v":24},{"id":5453,"t":"עׇרְלָתֽוֹ","p":"ערלתו","c":17,"v":24},{"id":5454,"t":"וְיִשְׁמָעֵ֣אל","p":"וישמעאל","c":17,"v":25},{"id":5455,"t":"בְּנ֔וֹ","p":"בנו","c":17,"v":25},{"id":5456,"t":"בֶּן","p":"בן","c":17,"v":25},{"id":5457,"t":"שְׁלֹ֥שׁ","p":"שלש","c":17,"v":25},{"id":5458,"t":"עֶשְׂרֵ֖ה","p":"עשרה","c":17,"v":25},{"id":5459,"t":"שָׁנָ֑ה","p":"שנה","c":17,"v":25},{"id":5460,"t":"בְּהִ֨מֹּל֔וֹ","p":"בהמלו","c":17,"v":25},{"id":5461,"t":"אֵ֖ת","p":"את","c":17,"v":25},{"id":5462,"t":"בְּשַׂ֥ר","p":"בשר","c":17,"v":25},{"id":5463,"t":"עׇרְלָתֽוֹ","p":"ערלתו","c":17,"v":25},{"id":5464,"t":"בְּעֶ֙צֶם֙","p":"בעצם","c":17,"v":26},{"id":5465,"t":"הַיּ֣וֹם","p":"היום","c":17,"v":26},{"id":5466,"t":"הַזֶּ֔ה","p":"הזה","c":17,"v":26},{"id":5467,"t":"נִמּ֖וֹל","p":"נמול","c":17,"v":26},{"id":5468,"t":"אַבְרָהָ֑ם","p":"אברהם","c":17,"v":26},{"id":5469,"t":"וְיִשְׁמָעֵ֖אל","p":"וישמעאל","c":17,"v":26},{"id":5470,"t":"בְּנֽוֹ","p":"בנו","c":17,"v":26},{"id":5471,"t":"וְכׇל","p":"וכל","c":17,"v":27},{"id":5472,"t":"אַנְשֵׁ֤י","p":"אנשי","c":17,"v":27},{"id":5473,"t":"בֵיתוֹ֙","p":"ביתו","c":17,"v":27},{"id":5474,"t":"יְלִ֣יד","p":"יליד","c":17,"v":27},{"id":5475,"t":"בָּ֔יִת","p":"בית","c":17,"v":27},{"id":5476,"t":"וּמִקְנַת","p":"ומקנת","c":17,"v":27},{"id":5477,"t":"כֶּ֖סֶף","p":"כסף","c":17,"v":27},{"id":5478,"t":"מֵאֵ֣ת","p":"מאת","c":17,"v":27},{"id":5479,"t":"בֶּן","p":"בן","c":17,"v":27},{"id":5480,"t":"נֵכָ֑ר","p":"נכר","c":17,"v":27},{"id":5481,"t":"נִמֹּ֖לוּ","p":"נמלו","c":17,"v":27},{"id":5482,"t":"אִתּֽוֹ","p":"אתו","c":17,"v":27}]